{
  "history": [
    {
      "timestamp": "2017-10-01T00:01:24.420774Z", 
      "value": 0.002579, 
      "value.currency": "USD", 
      "when": "a day ago"
    }, 
    {
      "timestamp": "2017-09-30T00:01:03.301374Z", 
      "value": 0.002545, 
      "value.currency": "USD", 
      "when": "2 days ago"
    }, 
    {
      "timestamp": "2017-09-29T00:01:07.847244Z", 
      "value": 0.002602, 
      "value.currency": "USD", 
      "when": "3 days ago"
    }, 
    {
      "timestamp": "2017-09-28T00:01:06.438311Z", 
      "value": 0.002398, 
      "value.currency": "USD", 
      "when": "4 days ago"
    }, 
    {
      "timestamp": "2017-09-27T00:00:31.161841Z", 
      "value": 0.004484, 
      "value.currency": "USD", 
      "when": "5 days ago"
    }, 
    {
      "timestamp": "2017-09-26T00:00:40.293691Z", 
      "value": 0.00212, 
      "value.currency": "USD", 
      "when": "6 days ago"
    }, 
    {
      "timestamp": "2017-09-25T00:00:38.114744Z", 
      "value": 0.001985, 
      "value.currency": "USD", 
      "when": "7 days ago"
    }, 
    {
      "timestamp": "2017-09-24T00:01:09.620883Z", 
      "value": 0.00197, 
      "value.currency": "USD", 
      "when": "8 days ago"
    }, 
    {
      "timestamp": "2017-09-22T00:01:19.815042Z", 
      "value": 0.001917, 
      "value.currency": "USD", 
      "when": "10 days ago"
    }, 
    {
      "timestamp": "2017-09-20T00:00:54.148459Z", 
      "value": 0.002596, 
      "value.currency": "USD", 
      "when": "12 days ago"
    }, 
    {
      "timestamp": "2017-09-19T00:00:54.016051Z", 
      "value": 0.002701, 
      "value.currency": "USD", 
      "when": "13 days ago"
    }, 
    {
      "timestamp": "2017-09-18T00:00:39.093004Z", 
      "value": 0.001927, 
      "value.currency": "USD", 
      "when": "14 days ago"
    }, 
    {
      "timestamp": "2017-09-16T00:00:54.166177Z", 
      "value": 0.001883, 
      "value.currency": "USD", 
      "when": "16 days ago"
    }, 
    {
      "timestamp": "2017-09-14T00:01:21.287958Z", 
      "value": 0.002102, 
      "value.currency": "USD", 
      "when": "18 days ago"
    }, 
    {
      "timestamp": "2017-09-13T00:00:52.356593Z", 
      "value": 0.002168, 
      "value.currency": "USD", 
      "when": "19 days ago"
    }, 
    {
      "timestamp": "2017-09-12T00:00:57.531985Z", 
      "value": 0.002147, 
      "value.currency": "USD", 
      "when": "20 days ago"
    }, 
    {
      "timestamp": "2017-09-08T00:01:19.691321Z", 
      "value": 0.002318, 
      "value.currency": "USD", 
      "when": "24 days ago"
    }, 
    {
      "timestamp": "2017-09-07T00:01:17.020639Z", 
      "value": 0.002312, 
      "value.currency": "USD", 
      "when": "25 days ago"
    }, 
    {
      "timestamp": "2017-09-05T00:01:08.192474Z", 
      "value": 0.002628, 
      "value.currency": "USD", 
      "when": "27 days ago"
    }, 
    {
      "timestamp": "2017-09-04T00:00:27.440204Z", 
      "value": 0.002815, 
      "value.currency": "USD", 
      "when": "28 days ago"
    }, 
    {
      "timestamp": "2017-09-03T00:00:47.351449Z", 
      "value": 0.002534, 
      "value.currency": "USD", 
      "when": "29 days ago"
    }, 
    {
      "timestamp": "2017-09-02T00:00:50.274682Z", 
      "value": 0.003025, 
      "value.currency": "USD", 
      "when": "30 days ago"
    }, 
    {
      "timestamp": "2017-09-01T00:01:47.096954Z", 
      "value": 0.002937, 
      "value.currency": "USD", 
      "when": "a month ago"
    }, 
    {
      "timestamp": "2017-08-31T00:00:57.934533Z", 
      "value": 0.00289, 
      "value.currency": "USD", 
      "when": "a month ago"
    }, 
    {
      "timestamp": "2017-08-30T00:01:18.071817Z", 
      "value": 0.00299, 
      "value.currency": "USD", 
      "when": "a month ago"
    }, 
    {
      "timestamp": "2017-08-29T00:01:15.837887Z", 
      "value": 0.002276, 
      "value.currency": "USD", 
      "when": "a month ago"
    }, 
    {
      "timestamp": "2017-08-28T00:00:55.354398Z", 
      "value": 0.002259, 
      "value.currency": "USD", 
      "when": "a month ago"
    }, 
    {
      "timestamp": "2017-08-26T00:00:23.475148Z", 
      "value": 0.002482, 
      "value.currency": "USD", 
      "when": "a month ago"
    }, 
    {
      "timestamp": "2017-08-25T00:01:24.045566Z", 
      "value": 0.002428, 
      "value.currency": "USD", 
      "when": "a month ago"
    }, 
    {
      "timestamp": "2017-08-24T00:02:09.865986Z", 
      "value": 0.00236, 
      "value.currency": "USD", 
      "when": "a month ago"
    }, 
    {
      "timestamp": "2017-08-23T00:02:37.128264Z", 
      "value": 0.00278, 
      "value.currency": "USD", 
      "when": "a month ago"
    }, 
    {
      "timestamp": "2017-08-22T00:02:11.505936Z", 
      "value": 0.002754, 
      "value.currency": "USD", 
      "when": "a month ago"
    }, 
    {
      "timestamp": "2017-08-21T00:01:58.569072Z", 
      "value": 0.002158, 
      "value.currency": "USD", 
      "when": "a month ago"
    }, 
    {
      "timestamp": "2017-08-20T00:02:15.919883Z", 
      "value": 0.002915, 
      "value.currency": "USD", 
      "when": "a month ago"
    }, 
    {
      "timestamp": "2017-08-19T00:02:14.803226Z", 
      "value": 0.002015, 
      "value.currency": "USD", 
      "when": "a month ago"
    }, 
    {
      "timestamp": "2017-08-18T00:02:03.799860Z", 
      "value": 0.00249, 
      "value.currency": "USD", 
      "when": "a month ago"
    }, 
    {
      "timestamp": "2017-08-17T00:01:39.409344Z", 
      "value": 0.002943, 
      "value.currency": "USD", 
      "when": "a month ago"
    }, 
    {
      "timestamp": "2017-08-16T00:01:57.457480Z", 
      "value": 0.00278, 
      "value.currency": "USD", 
      "when": "a month ago"
    }, 
    {
      "timestamp": "2017-08-15T00:02:01.288898Z", 
      "value": 0.002891, 
      "value.currency": "USD", 
      "when": "a month ago"
    }, 
    {
      "timestamp": "2017-08-14T00:01:50.062321Z", 
      "value": 0.00272, 
      "value.currency": "USD", 
      "when": "a month ago"
    }, 
    {
      "timestamp": "2017-08-13T00:02:05.989103Z", 
      "value": 0.002594, 
      "value.currency": "USD", 
      "when": "a month ago"
    }, 
    {
      "timestamp": "2017-08-12T00:02:31.752677Z", 
      "value": 0.002484, 
      "value.currency": "USD", 
      "when": "a month ago"
    }, 
    {
      "timestamp": "2017-08-11T00:02:10.298724Z", 
      "value": 0.002289, 
      "value.currency": "USD", 
      "when": "a month ago"
    }, 
    {
      "timestamp": "2017-08-10T00:01:42.788637Z", 
      "value": 0.002774, 
      "value.currency": "USD", 
      "when": "a month ago"
    }, 
    {
      "timestamp": "2017-08-09T00:02:40.197068Z", 
      "value": 0.002536, 
      "value.currency": "USD", 
      "when": "a month ago"
    }, 
    {
      "timestamp": "2017-08-08T00:02:06.011209Z", 
      "value": 0.002473, 
      "value.currency": "USD", 
      "when": "a month ago"
    }, 
    {
      "timestamp": "2017-08-07T00:01:37.125898Z", 
      "value": 0.002356, 
      "value.currency": "USD", 
      "when": "a month ago"
    }, 
    {
      "timestamp": "2017-08-06T00:02:48.268968Z", 
      "value": 0.002245, 
      "value.currency": "USD", 
      "when": "a month ago"
    }, 
    {
      "timestamp": "2017-08-05T00:01:36.586609Z", 
      "value": 0.001971, 
      "value.currency": "USD", 
      "when": "a month ago"
    }, 
    {
      "timestamp": "2017-08-04T00:01:39.022769Z", 
      "value": 0.001896, 
      "value.currency": "USD", 
      "when": "a month ago"
    }, 
    {
      "timestamp": "2017-08-03T00:02:08.519966Z", 
      "value": 0.001808, 
      "value.currency": "USD", 
      "when": "a month ago"
    }, 
    {
      "timestamp": "2017-08-02T00:01:39.231385Z", 
      "value": 0.001829, 
      "value.currency": "USD", 
      "when": "2 months ago"
    }, 
    {
      "timestamp": "2017-08-01T00:02:06.130006Z", 
      "value": 0.002146, 
      "value.currency": "USD", 
      "when": "2 months ago"
    }, 
    {
      "timestamp": "2017-07-31T00:02:13.040304Z", 
      "value": 0.00219, 
      "value.currency": "USD", 
      "when": "2 months ago"
    }, 
    {
      "timestamp": "2017-07-30T00:01:55.790953Z", 
      "value": 0.001848, 
      "value.currency": "USD", 
      "when": "2 months ago"
    }, 
    {
      "timestamp": "2017-07-29T00:02:04.490685Z", 
      "value": 0.002736, 
      "value.currency": "USD", 
      "when": "2 months ago"
    }, 
    {
      "timestamp": "2017-07-28T00:02:35.021072Z", 
      "value": 0.001645, 
      "value.currency": "USD", 
      "when": "2 months ago"
    }, 
    {
      "timestamp": "2017-07-27T00:02:21.033632Z", 
      "value": 0.001511, 
      "value.currency": "USD", 
      "when": "2 months ago"
    }, 
    {
      "timestamp": "2017-07-26T00:02:35.762496Z", 
      "value": 0.001535, 
      "value.currency": "USD", 
      "when": "2 months ago"
    }, 
    {
      "timestamp": "2017-07-25T00:02:07.022684Z", 
      "value": 0.0016, 
      "value.currency": "USD", 
      "when": "2 months ago"
    }, 
    {
      "timestamp": "2017-07-24T00:02:05.934627Z", 
      "value": 0.00157, 
      "value.currency": "USD", 
      "when": "2 months ago"
    }, 
    {
      "timestamp": "2017-07-23T00:01:59.961077Z", 
      "value": 0.001528, 
      "value.currency": "USD", 
      "when": "2 months ago"
    }, 
    {
      "timestamp": "2017-07-22T00:01:41.247898Z", 
      "value": 0.001414, 
      "value.currency": "USD", 
      "when": "2 months ago"
    }, 
    {
      "timestamp": "2017-07-21T00:01:38.065155Z", 
      "value": 0.001434, 
      "value.currency": "USD", 
      "when": "2 months ago"
    }, 
    {
      "timestamp": "2017-07-20T00:02:20.249930Z", 
      "value": 0.001108, 
      "value.currency": "USD", 
      "when": "2 months ago"
    }, 
    {
      "timestamp": "2017-07-19T00:01:57.657433Z", 
      "value": 0.001127, 
      "value.currency": "USD", 
      "when": "2 months ago"
    }, 
    {
      "timestamp": "2017-07-18T00:02:00.085942Z", 
      "value": 0.001463, 
      "value.currency": "USD", 
      "when": "2 months ago"
    }, 
    {
      "timestamp": "2017-07-17T00:01:51.873388Z", 
      "value": 0.000943, 
      "value.currency": "USD", 
      "when": "2 months ago"
    }, 
    {
      "timestamp": "2017-07-16T00:01:49.610347Z", 
      "value": 0.001195, 
      "value.currency": "USD", 
      "when": "2 months ago"
    }, 
    {
      "timestamp": "2017-07-15T00:02:00.140545Z", 
      "value": 0.001333, 
      "value.currency": "USD", 
      "when": "2 months ago"
    }, 
    {
      "timestamp": "2017-07-14T00:01:59.811334Z", 
      "value": 0.00164, 
      "value.currency": "USD", 
      "when": "2 months ago"
    }, 
    {
      "timestamp": "2017-07-12T00:01:53.992809Z", 
      "value": 0.000973, 
      "value.currency": "USD", 
      "when": "2 months ago"
    }, 
    {
      "timestamp": "2017-07-11T00:03:02.244425Z", 
      "value": 0.000985, 
      "value.currency": "USD", 
      "when": "2 months ago"
    }, 
    {
      "timestamp": "2017-07-10T00:01:55.528498Z", 
      "value": 0.001375, 
      "value.currency": "USD", 
      "when": "2 months ago"
    }, 
    {
      "timestamp": "2017-07-09T00:01:57.050580Z", 
      "value": 0.001019, 
      "value.currency": "USD", 
      "when": "2 months ago"
    }, 
    {
      "timestamp": "2017-07-08T00:01:46.335153Z", 
      "value": 0.0008, 
      "value.currency": "USD", 
      "when": "2 months ago"
    }, 
    {
      "timestamp": "2017-07-07T00:02:01.411483Z", 
      "value": 0.001238, 
      "value.currency": "USD", 
      "when": "2 months ago"
    }, 
    {
      "timestamp": "2017-07-06T00:02:25.125260Z", 
      "value": 0.001247, 
      "value.currency": "USD", 
      "when": "2 months ago"
    }, 
    {
      "timestamp": "2017-07-05T00:01:50.791838Z", 
      "value": 0.001037, 
      "value.currency": "USD", 
      "when": "2 months ago"
    }, 
    {
      "timestamp": "2017-07-04T00:01:59.236556Z", 
      "value": 0.001017, 
      "value.currency": "USD", 
      "when": "2 months ago"
    }, 
    {
      "timestamp": "2017-07-02T00:02:05.675269Z", 
      "value": 0.000932, 
      "value.currency": "USD", 
      "when": "3 months ago"
    }, 
    {
      "timestamp": "2017-06-29T00:01:23.588246Z", 
      "value": 0.000996, 
      "value.currency": "USD", 
      "when": "3 months ago"
    }, 
    {
      "timestamp": "2017-06-28T00:02:10.933611Z", 
      "value": 0.000962, 
      "value.currency": "USD", 
      "when": "3 months ago"
    }, 
    {
      "timestamp": "2017-06-26T00:01:59.078197Z", 
      "value": 0.000914, 
      "value.currency": "USD", 
      "when": "3 months ago"
    }, 
    {
      "timestamp": "2017-06-24T00:01:47.726455Z", 
      "value": 0.001007, 
      "value.currency": "USD", 
      "when": "3 months ago"
    }, 
    {
      "timestamp": "2017-06-23T00:02:05.174112Z", 
      "value": 0.000924, 
      "value.currency": "USD", 
      "when": "3 months ago"
    }, 
    {
      "timestamp": "2017-06-22T00:01:53.470597Z", 
      "value": 0.000874, 
      "value.currency": "USD", 
      "when": "3 months ago"
    }, 
    {
      "timestamp": "2017-06-21T00:02:08.647980Z", 
      "value": 0.000874, 
      "value.currency": "USD", 
      "when": "3 months ago"
    }, 
    {
      "timestamp": "2017-06-20T00:02:38.228370Z", 
      "value": 0.000874, 
      "value.currency": "USD", 
      "when": "3 months ago"
    }, 
    {
      "timestamp": "2017-06-18T00:01:27.323655Z", 
      "value": 0.000799, 
      "value.currency": "USD", 
      "when": "3 months ago"
    }, 
    {
      "timestamp": "2017-06-15T00:02:12.046867Z", 
      "value": 0.000764, 
      "value.currency": "USD", 
      "when": "3 months ago"
    }, 
    {
      "timestamp": "2017-06-13T00:01:57.646620Z", 
      "value": 0.000787, 
      "value.currency": "USD", 
      "when": "3 months ago"
    }, 
    {
      "timestamp": "2017-06-12T00:01:41.686802Z", 
      "value": 0.000894, 
      "value.currency": "USD", 
      "when": "3 months ago"
    }, 
    {
      "timestamp": "2017-06-11T00:01:50.080650Z", 
      "value": 0.000926, 
      "value.currency": "USD", 
      "when": "3 months ago"
    }, 
    {
      "timestamp": "2017-06-10T00:02:01.252527Z", 
      "value": 0.001038, 
      "value.currency": "USD", 
      "when": "3 months ago"
    }, 
    {
      "timestamp": "2017-06-09T00:01:44.228880Z", 
      "value": 0.001038, 
      "value.currency": "USD", 
      "when": "3 months ago"
    }, 
    {
      "timestamp": "2017-06-08T00:01:42.560347Z", 
      "value": 0.000776, 
      "value.currency": "USD", 
      "when": "3 months ago"
    }, 
    {
      "timestamp": "2017-06-07T00:02:06.245186Z", 
      "value": 0.000802, 
      "value.currency": "USD", 
      "when": "3 months ago"
    }, 
    {
      "timestamp": "2017-06-06T00:01:33.743841Z", 
      "value": 0.000833, 
      "value.currency": "USD", 
      "when": "3 months ago"
    }, 
    {
      "timestamp": "2017-06-05T00:01:44.632596Z", 
      "value": 0.000805, 
      "value.currency": "USD", 
      "when": "3 months ago"
    }, 
    {
      "timestamp": "2017-06-04T00:01:35.435025Z", 
      "value": 0.000527, 
      "value.currency": "USD", 
      "when": "3 months ago"
    }, 
    {
      "timestamp": "2017-06-03T00:01:25.204412Z", 
      "value": 0.000503, 
      "value.currency": "USD", 
      "when": "3 months ago"
    }, 
    {
      "timestamp": "2017-06-02T00:01:20.496439Z", 
      "value": 0.000429, 
      "value.currency": "USD", 
      "when": "4 months ago"
    }, 
    {
      "timestamp": "2017-06-01T00:01:21.233276Z", 
      "value": 0.000793, 
      "value.currency": "USD", 
      "when": "4 months ago"
    }, 
    {
      "timestamp": "2017-05-31T00:01:31.864523Z", 
      "value": 0.000283, 
      "value.currency": "USD", 
      "when": "4 months ago"
    }, 
    {
      "timestamp": "2017-05-30T00:01:17.792925Z", 
      "value": 0.000327, 
      "value.currency": "USD", 
      "when": "4 months ago"
    }, 
    {
      "timestamp": "2017-05-29T00:01:28.499507Z", 
      "value": 0.000373, 
      "value.currency": "USD", 
      "when": "4 months ago"
    }, 
    {
      "timestamp": "2017-05-28T00:01:28.057815Z", 
      "value": 0.000255, 
      "value.currency": "USD", 
      "when": "4 months ago"
    }, 
    {
      "timestamp": "2017-05-27T00:01:27.345343Z", 
      "value": 0.000678, 
      "value.currency": "USD", 
      "when": "4 months ago"
    }, 
    {
      "timestamp": "2017-05-26T00:01:10.717197Z", 
      "value": 0.00074, 
      "value.currency": "USD", 
      "when": "4 months ago"
    }, 
    {
      "timestamp": "2017-05-25T00:01:35.397636Z", 
      "value": 0.000829, 
      "value.currency": "USD", 
      "when": "4 months ago"
    }, 
    {
      "timestamp": "2017-05-24T00:01:44.894699Z", 
      "value": 0.000678, 
      "value.currency": "USD", 
      "when": "4 months ago"
    }, 
    {
      "timestamp": "2017-05-23T00:01:21.484193Z", 
      "value": 0.000802, 
      "value.currency": "USD", 
      "when": "4 months ago"
    }, 
    {
      "timestamp": "2017-05-22T00:01:10.313650Z", 
      "value": 0.00063, 
      "value.currency": "USD", 
      "when": "4 months ago"
    }, 
    {
      "timestamp": "2017-05-21T00:01:23.839355Z", 
      "value": 0.000655, 
      "value.currency": "USD", 
      "when": "4 months ago"
    }, 
    {
      "timestamp": "2017-05-20T00:01:23.352835Z", 
      "value": 0.000609, 
      "value.currency": "USD", 
      "when": "4 months ago"
    }, 
    {
      "timestamp": "2017-05-18T00:01:03.599069Z", 
      "value": 0.000566, 
      "value.currency": "USD", 
      "when": "4 months ago"
    }, 
    {
      "timestamp": "2017-05-17T00:01:13.481653Z", 
      "value": 0.000539, 
      "value.currency": "USD", 
      "when": "4 months ago"
    }, 
    {
      "timestamp": "2017-05-16T00:01:13.118987Z", 
      "value": 0.00019, 
      "value.currency": "USD", 
      "when": "4 months ago"
    }, 
    {
      "timestamp": "2017-05-15T00:01:40.600982Z", 
      "value": 0.000197, 
      "value.currency": "USD", 
      "when": "4 months ago"
    }, 
    {
      "timestamp": "2017-05-14T00:01:35.178311Z", 
      "value": 0.000337, 
      "value.currency": "USD", 
      "when": "4 months ago"
    }, 
    {
      "timestamp": "2017-05-13T00:01:27.802072Z", 
      "value": 0.00034, 
      "value.currency": "USD", 
      "when": "4 months ago"
    }, 
    {
      "timestamp": "2017-05-12T00:01:07.677207Z", 
      "value": 0.000475, 
      "value.currency": "USD", 
      "when": "4 months ago"
    }, 
    {
      "timestamp": "2017-05-11T00:01:34.680732Z", 
      "value": 0.000316, 
      "value.currency": "USD", 
      "when": "4 months ago"
    }, 
    {
      "timestamp": "2017-05-10T00:01:14.127508Z", 
      "value": 0.000354, 
      "value.currency": "USD", 
      "when": "4 months ago"
    }, 
    {
      "timestamp": "2017-05-09T00:01:13.478984Z", 
      "value": 0.000534, 
      "value.currency": "USD", 
      "when": "4 months ago"
    }, 
    {
      "timestamp": "2017-05-08T00:01:49.072248Z", 
      "value": 0.000495, 
      "value.currency": "USD", 
      "when": "4 months ago"
    }, 
    {
      "timestamp": "2017-05-07T00:01:34.731150Z", 
      "value": 0.000489, 
      "value.currency": "USD", 
      "when": "4 months ago"
    }, 
    {
      "timestamp": "2017-05-06T00:01:38.939065Z", 
      "value": 0.000482, 
      "value.currency": "USD", 
      "when": "4 months ago"
    }, 
    {
      "timestamp": "2017-05-05T00:01:40.437390Z", 
      "value": 0.000397, 
      "value.currency": "USD", 
      "when": "4 months ago"
    }, 
    {
      "timestamp": "2017-05-04T00:01:33.467593Z", 
      "value": 0.000264, 
      "value.currency": "USD", 
      "when": "4 months ago"
    }, 
    {
      "timestamp": "2017-05-02T00:01:40.876569Z", 
      "value": 0.000411, 
      "value.currency": "USD", 
      "when": "5 months ago"
    }, 
    {
      "timestamp": "2017-05-01T00:01:14.652923Z", 
      "value": 0.000299, 
      "value.currency": "USD", 
      "when": "5 months ago"
    }, 
    {
      "timestamp": "2017-04-30T00:01:12.564130Z", 
      "value": 0.000279, 
      "value.currency": "USD", 
      "when": "5 months ago"
    }, 
    {
      "timestamp": "2017-04-29T00:01:21.580311Z", 
      "value": 0.000206, 
      "value.currency": "USD", 
      "when": "5 months ago"
    }, 
    {
      "timestamp": "2017-04-28T00:01:11.909506Z", 
      "value": 0.000165, 
      "value.currency": "USD", 
      "when": "5 months ago"
    }, 
    {
      "timestamp": "2017-04-27T00:01:01.304433Z", 
      "value": 0.000339, 
      "value.currency": "USD", 
      "when": "5 months ago"
    }, 
    {
      "timestamp": "2017-04-26T00:01:12.382814Z", 
      "value": 0.000234, 
      "value.currency": "USD", 
      "when": "5 months ago"
    }, 
    {
      "timestamp": "2017-04-25T00:01:18.945708Z", 
      "value": 0.00021, 
      "value.currency": "USD", 
      "when": "5 months ago"
    }, 
    {
      "timestamp": "2017-04-24T00:01:23.553765Z", 
      "value": 0.000203, 
      "value.currency": "USD", 
      "when": "5 months ago"
    }, 
    {
      "timestamp": "2017-04-23T00:01:40.588282Z", 
      "value": 0.000357, 
      "value.currency": "USD", 
      "when": "5 months ago"
    }, 
    {
      "timestamp": "2017-04-22T00:01:29.721276Z", 
      "value": 0.000242, 
      "value.currency": "USD", 
      "when": "5 months ago"
    }, 
    {
      "timestamp": "2017-04-21T00:01:26.235134Z", 
      "value": 0.000358, 
      "value.currency": "USD", 
      "when": "5 months ago"
    }, 
    {
      "timestamp": "2017-04-20T00:01:48.516196Z", 
      "value": 0.000351, 
      "value.currency": "USD", 
      "when": "5 months ago"
    }, 
    {
      "timestamp": "2017-04-19T00:02:03.163916Z", 
      "value": 0.000339, 
      "value.currency": "USD", 
      "when": "5 months ago"
    }, 
    {
      "timestamp": "2017-04-18T00:01:35.687171Z", 
      "value": 0.000323, 
      "value.currency": "USD", 
      "when": "5 months ago"
    }, 
    {
      "timestamp": "2017-04-17T00:01:18.182070Z", 
      "value": 0.000279, 
      "value.currency": "USD", 
      "when": "5 months ago"
    }, 
    {
      "timestamp": "2017-04-16T00:01:30.629653Z", 
      "value": 0.000214, 
      "value.currency": "USD", 
      "when": "5 months ago"
    }, 
    {
      "timestamp": "2017-04-15T00:01:17.223830Z", 
      "value": 0.000283, 
      "value.currency": "USD", 
      "when": "5 months ago"
    }, 
    {
      "timestamp": "2017-04-14T00:01:18.432662Z", 
      "value": 0.000246, 
      "value.currency": "USD", 
      "when": "5 months ago"
    }, 
    {
      "timestamp": "2017-04-13T00:01:06.658201Z", 
      "value": 0.000216, 
      "value.currency": "USD", 
      "when": "5 months ago"
    }, 
    {
      "timestamp": "2017-04-12T00:01:07.717421Z", 
      "value": 0.000229, 
      "value.currency": "USD", 
      "when": "5 months ago"
    }, 
    {
      "timestamp": "2017-04-11T00:01:27.266147Z", 
      "value": 0.000392, 
      "value.currency": "USD", 
      "when": "5 months ago"
    }, 
    {
      "timestamp": "2017-04-10T00:01:28.918662Z", 
      "value": 0.000391, 
      "value.currency": "USD", 
      "when": "5 months ago"
    }, 
    {
      "timestamp": "2017-04-09T00:01:26.137023Z", 
      "value": 0.000176, 
      "value.currency": "USD", 
      "when": "5 months ago"
    }, 
    {
      "timestamp": "2017-04-08T00:01:24.685327Z", 
      "value": 0.000418, 
      "value.currency": "USD", 
      "when": "5 months ago"
    }, 
    {
      "timestamp": "2017-04-07T00:01:36.615371Z", 
      "value": 0.000414, 
      "value.currency": "USD", 
      "when": "5 months ago"
    }, 
    {
      "timestamp": "2017-04-06T00:01:18.452316Z", 
      "value": 0.000181, 
      "value.currency": "USD", 
      "when": "5 months ago"
    }, 
    {
      "timestamp": "2017-04-05T00:01:06.403382Z", 
      "value": 0.000102, 
      "value.currency": "USD", 
      "when": "5 months ago"
    }, 
    {
      "timestamp": "2017-04-04T00:01:39.906570Z", 
      "value": 0.000112, 
      "value.currency": "USD", 
      "when": "5 months ago"
    }, 
    {
      "timestamp": "2017-04-03T00:01:12.714333Z", 
      "value": 0.000135, 
      "value.currency": "USD", 
      "when": "5 months ago"
    }, 
    {
      "timestamp": "2017-04-02T00:01:42.129857Z", 
      "value": 9.7e-05, 
      "value.currency": "USD", 
      "when": "6 months ago"
    }, 
    {
      "timestamp": "2017-04-01T00:01:21.189773Z", 
      "value": 0.000101, 
      "value.currency": "USD", 
      "when": "6 months ago"
    }, 
    {
      "timestamp": "2017-03-31T00:01:01.400181Z", 
      "value": 0.000103, 
      "value.currency": "USD", 
      "when": "6 months ago"
    }, 
    {
      "timestamp": "2017-03-30T00:01:25.439280Z", 
      "value": 0.000173, 
      "value.currency": "USD", 
      "when": "6 months ago"
    }, 
    {
      "timestamp": "2017-03-29T00:01:08.918870Z", 
      "value": 0.000126, 
      "value.currency": "USD", 
      "when": "6 months ago"
    }, 
    {
      "timestamp": "2017-03-28T00:01:26.067649Z", 
      "value": 0.000186, 
      "value.currency": "USD", 
      "when": "6 months ago"
    }, 
    {
      "timestamp": "2017-03-27T00:01:17.789606Z", 
      "value": 0.000116, 
      "value.currency": "USD", 
      "when": "6 months ago"
    }, 
    {
      "timestamp": "2017-03-26T00:01:14.250445Z", 
      "value": 0.000109, 
      "value.currency": "USD", 
      "when": "6 months ago"
    }, 
    {
      "timestamp": "2017-03-25T00:01:00.842866Z", 
      "value": 0.000168, 
      "value.currency": "USD", 
      "when": "6 months ago"
    }, 
    {
      "timestamp": "2017-03-24T00:01:38.085360Z", 
      "value": 0.000133, 
      "value.currency": "USD", 
      "when": "6 months ago"
    }, 
    {
      "timestamp": "2017-03-23T00:01:21.704596Z", 
      "value": 0.000155, 
      "value.currency": "USD", 
      "when": "6 months ago"
    }, 
    {
      "timestamp": "2017-03-22T00:01:30.422302Z", 
      "value": 0.000202, 
      "value.currency": "USD", 
      "when": "6 months ago"
    }, 
    {
      "timestamp": "2017-03-21T00:01:52.019825Z", 
      "value": 0.000116, 
      "value.currency": "USD", 
      "when": "6 months ago"
    }, 
    {
      "timestamp": "2017-03-20T00:01:03.873081Z", 
      "value": 0.000234, 
      "value.currency": "USD", 
      "when": "6 months ago"
    }, 
    {
      "timestamp": "2017-03-19T00:01:09.028443Z", 
      "value": 0.000186, 
      "value.currency": "USD", 
      "when": "6 months ago"
    }, 
    {
      "timestamp": "2017-03-18T00:00:58.681167Z", 
      "value": 0.000228, 
      "value.currency": "USD", 
      "when": "6 months ago"
    }, 
    {
      "timestamp": "2017-03-17T00:01:01.563113Z", 
      "value": 0.000293, 
      "value.currency": "USD", 
      "when": "6 months ago"
    }, 
    {
      "timestamp": "2017-03-16T00:01:26.997645Z", 
      "value": 0.000335, 
      "value.currency": "USD", 
      "when": "6 months ago"
    }, 
    {
      "timestamp": "2017-03-15T00:01:01.094178Z", 
      "value": 0.000273, 
      "value.currency": "USD", 
      "when": "6 months ago"
    }, 
    {
      "timestamp": "2017-03-14T00:01:49.652790Z", 
      "value": 0.000197, 
      "value.currency": "USD", 
      "when": "6 months ago"
    }, 
    {
      "timestamp": "2017-03-13T00:01:05.757199Z", 
      "value": 0.000196, 
      "value.currency": "USD", 
      "when": "6 months ago"
    }, 
    {
      "timestamp": "2017-03-12T01:01:35.088012Z", 
      "value": 0.000217, 
      "value.currency": "USD", 
      "when": "6 months ago"
    }, 
    {
      "timestamp": "2017-03-11T01:01:45.308977Z", 
      "value": 0.000201, 
      "value.currency": "USD", 
      "when": "6 months ago"
    }, 
    {
      "timestamp": "2017-03-10T01:02:19.620937Z", 
      "value": 0.000238, 
      "value.currency": "USD", 
      "when": "6 months ago"
    }, 
    {
      "timestamp": "2017-03-09T01:01:03.191605Z", 
      "value": 0.000208, 
      "value.currency": "USD", 
      "when": "6 months ago"
    }, 
    {
      "timestamp": "2017-03-08T01:01:38.555658Z", 
      "value": 0.000208, 
      "value.currency": "USD", 
      "when": "6 months ago"
    }, 
    {
      "timestamp": "2017-03-07T01:00:54.023347Z", 
      "value": 0.000216, 
      "value.currency": "USD", 
      "when": "6 months ago"
    }, 
    {
      "timestamp": "2017-03-06T01:00:59.994929Z", 
      "value": 0.00022, 
      "value.currency": "USD", 
      "when": "6 months ago"
    }, 
    {
      "timestamp": "2017-03-05T01:00:59.580816Z", 
      "value": 0.000264, 
      "value.currency": "USD", 
      "when": "6 months ago"
    }, 
    {
      "timestamp": "2017-03-04T01:01:11.273885Z", 
      "value": 0.00025, 
      "value.currency": "USD", 
      "when": "6 months ago"
    }, 
    {
      "timestamp": "2017-03-03T01:01:17.555549Z", 
      "value": 0.000188, 
      "value.currency": "USD", 
      "when": "6 months ago"
    }, 
    {
      "timestamp": "2017-03-02T01:01:15.697679Z", 
      "value": 0.000293, 
      "value.currency": "USD", 
      "when": "7 months ago"
    }, 
    {
      "timestamp": "2017-02-28T01:01:23.472370Z", 
      "value": 0.000231, 
      "value.currency": "USD", 
      "when": "7 months ago"
    }, 
    {
      "timestamp": "2017-02-27T01:01:12.482225Z", 
      "value": 0.000315, 
      "value.currency": "USD", 
      "when": "7 months ago"
    }, 
    {
      "timestamp": "2017-02-26T01:01:38.302027Z", 
      "value": 0.000216, 
      "value.currency": "USD", 
      "when": "7 months ago"
    }, 
    {
      "timestamp": "2017-02-25T01:00:59.726986Z", 
      "value": 0.000228, 
      "value.currency": "USD", 
      "when": "7 months ago"
    }, 
    {
      "timestamp": "2017-02-24T01:01:32.742838Z", 
      "value": 0.000269, 
      "value.currency": "USD", 
      "when": "7 months ago"
    }, 
    {
      "timestamp": "2017-02-23T01:01:08.774217Z", 
      "value": 0.000279, 
      "value.currency": "USD", 
      "when": "7 months ago"
    }, 
    {
      "timestamp": "2017-02-22T01:01:19.330424Z", 
      "value": 0.00029, 
      "value.currency": "USD", 
      "when": "7 months ago"
    }, 
    {
      "timestamp": "2017-02-21T01:01:02.741820Z", 
      "value": 0.000245, 
      "value.currency": "USD", 
      "when": "7 months ago"
    }, 
    {
      "timestamp": "2017-02-20T01:01:12.142040Z", 
      "value": 0.00021, 
      "value.currency": "USD", 
      "when": "7 months ago"
    }, 
    {
      "timestamp": "2017-02-19T01:00:58.692763Z", 
      "value": 0.000196, 
      "value.currency": "USD", 
      "when": "7 months ago"
    }, 
    {
      "timestamp": "2017-02-18T01:01:04.818218Z", 
      "value": 0.000232, 
      "value.currency": "USD", 
      "when": "7 months ago"
    }, 
    {
      "timestamp": "2017-02-17T01:01:09.910082Z", 
      "value": 0.000262, 
      "value.currency": "USD", 
      "when": "7 months ago"
    }, 
    {
      "timestamp": "2017-02-16T01:01:12.784179Z", 
      "value": 0.00026, 
      "value.currency": "USD", 
      "when": "7 months ago"
    }, 
    {
      "timestamp": "2017-02-15T01:01:37.230444Z", 
      "value": 0.000221, 
      "value.currency": "USD", 
      "when": "7 months ago"
    }, 
    {
      "timestamp": "2017-02-14T01:01:14.713305Z", 
      "value": 0.000218, 
      "value.currency": "USD", 
      "when": "7 months ago"
    }, 
    {
      "timestamp": "2017-02-13T01:00:55.662321Z", 
      "value": 0.000219, 
      "value.currency": "USD", 
      "when": "7 months ago"
    }, 
    {
      "timestamp": "2017-02-12T01:01:14.356688Z", 
      "value": 0.000207, 
      "value.currency": "USD", 
      "when": "7 months ago"
    }, 
    {
      "timestamp": "2017-02-11T01:01:13.660290Z", 
      "value": 0.00023, 
      "value.currency": "USD", 
      "when": "7 months ago"
    }, 
    {
      "timestamp": "2017-02-10T01:01:45.302150Z", 
      "value": 0.000222, 
      "value.currency": "USD", 
      "when": "7 months ago"
    }, 
    {
      "timestamp": "2017-02-09T01:00:59.972666Z", 
      "value": 0.000319, 
      "value.currency": "USD", 
      "when": "7 months ago"
    }, 
    {
      "timestamp": "2017-02-08T01:01:18.013709Z", 
      "value": 0.000319, 
      "value.currency": "USD", 
      "when": "7 months ago"
    }, 
    {
      "timestamp": "2017-02-07T01:01:06.048219Z", 
      "value": 0.000281, 
      "value.currency": "USD", 
      "when": "7 months ago"
    }, 
    {
      "timestamp": "2017-02-06T01:01:41.583373Z", 
      "value": 0.000304, 
      "value.currency": "USD", 
      "when": "7 months ago"
    }, 
    {
      "timestamp": "2017-02-05T01:01:19.400088Z", 
      "value": 0.000305, 
      "value.currency": "USD", 
      "when": "7 months ago"
    }, 
    {
      "timestamp": "2017-02-04T01:01:01.159750Z", 
      "value": 0.00042, 
      "value.currency": "USD", 
      "when": "7 months ago"
    }, 
    {
      "timestamp": "2017-02-03T01:01:08.658814Z", 
      "value": 0.000362, 
      "value.currency": "USD", 
      "when": "7 months ago"
    }, 
    {
      "timestamp": "2017-02-02T01:01:17.866781Z", 
      "value": 0.000336, 
      "value.currency": "USD", 
      "when": "7 months ago"
    }, 
    {
      "timestamp": "2017-02-01T01:00:56.012951Z", 
      "value": 0.000281, 
      "value.currency": "USD", 
      "when": "7 months ago"
    }, 
    {
      "timestamp": "2017-01-31T01:01:00.199833Z", 
      "value": 0.000294, 
      "value.currency": "USD", 
      "when": "8 months ago"
    }, 
    {
      "timestamp": "2017-01-30T01:00:56.673317Z", 
      "value": 0.000259, 
      "value.currency": "USD", 
      "when": "8 months ago"
    }, 
    {
      "timestamp": "2017-01-29T01:01:32.138612Z", 
      "value": 0.000294, 
      "value.currency": "USD", 
      "when": "8 months ago"
    }, 
    {
      "timestamp": "2017-01-28T01:15:24.541526Z", 
      "value": 0.000267, 
      "value.currency": "USD", 
      "when": "8 months ago"
    }, 
    {
      "timestamp": "2017-01-27T01:01:29.781502Z", 
      "value": 0.000253, 
      "value.currency": "USD", 
      "when": "8 months ago"
    }, 
    {
      "timestamp": "2017-01-26T01:00:57.395958Z", 
      "value": 0.00027, 
      "value.currency": "USD", 
      "when": "8 months ago"
    }, 
    {
      "timestamp": "2017-01-25T01:00:54.467579Z", 
      "value": 0.000223, 
      "value.currency": "USD", 
      "when": "8 months ago"
    }, 
    {
      "timestamp": "2017-01-24T01:01:12.726122Z", 
      "value": 0.000196, 
      "value.currency": "USD", 
      "when": "8 months ago"
    }, 
    {
      "timestamp": "2017-01-23T01:00:57.320676Z", 
      "value": 0.000237, 
      "value.currency": "USD", 
      "when": "8 months ago"
    }, 
    {
      "timestamp": "2017-01-22T01:01:35.510858Z", 
      "value": 0.000249, 
      "value.currency": "USD", 
      "when": "8 months ago"
    }, 
    {
      "timestamp": "2017-01-21T01:01:07.686714Z", 
      "value": 0.000259, 
      "value.currency": "USD", 
      "when": "8 months ago"
    }, 
    {
      "timestamp": "2017-01-20T01:02:07.978587Z", 
      "value": 0.00026, 
      "value.currency": "USD", 
      "when": "8 months ago"
    }, 
    {
      "timestamp": "2017-01-19T01:02:14.724944Z", 
      "value": 0.000309, 
      "value.currency": "USD", 
      "when": "8 months ago"
    }, 
    {
      "timestamp": "2017-01-18T01:02:08.551637Z", 
      "value": 0.000254, 
      "value.currency": "USD", 
      "when": "8 months ago"
    }, 
    {
      "timestamp": "2017-01-17T01:03:00.072642Z", 
      "value": 0.00034, 
      "value.currency": "USD", 
      "when": "8 months ago"
    }, 
    {
      "timestamp": "2017-01-16T01:01:56.782247Z", 
      "value": 0.00023, 
      "value.currency": "USD", 
      "when": "8 months ago"
    }, 
    {
      "timestamp": "2017-01-15T01:02:11.954041Z", 
      "value": 0.000187, 
      "value.currency": "USD", 
      "when": "8 months ago"
    }, 
    {
      "timestamp": "2017-01-14T01:02:26.608766Z", 
      "value": 0.000287, 
      "value.currency": "USD", 
      "when": "8 months ago"
    }, 
    {
      "timestamp": "2017-01-13T01:02:09.980931Z", 
      "value": 0.000177, 
      "value.currency": "USD", 
      "when": "8 months ago"
    }, 
    {
      "timestamp": "2017-01-12T01:01:56.891993Z", 
      "value": 0.000164, 
      "value.currency": "USD", 
      "when": "8 months ago"
    }, 
    {
      "timestamp": "2017-01-11T01:02:43.230294Z", 
      "value": 0.000188, 
      "value.currency": "USD", 
      "when": "8 months ago"
    }, 
    {
      "timestamp": "2017-01-10T01:02:08.736955Z", 
      "value": 0.00028, 
      "value.currency": "USD", 
      "when": "8 months ago"
    }, 
    {
      "timestamp": "2017-01-09T01:01:30.322613Z", 
      "value": 0.000264, 
      "value.currency": "USD", 
      "when": "8 months ago"
    }, 
    {
      "timestamp": "2017-01-08T01:01:28.432926Z", 
      "value": 0.000187, 
      "value.currency": "USD", 
      "when": "8 months ago"
    }, 
    {
      "timestamp": "2017-01-07T01:01:42.496943Z", 
      "value": 0.000262, 
      "value.currency": "USD", 
      "when": "8 months ago"
    }, 
    {
      "timestamp": "2017-01-06T01:01:34.304826Z", 
      "value": 0.000204, 
      "value.currency": "USD", 
      "when": "8 months ago"
    }, 
    {
      "timestamp": "2017-01-05T01:01:44.434744Z", 
      "value": 0.000346, 
      "value.currency": "USD", 
      "when": "8 months ago"
    }, 
    {
      "timestamp": "2017-01-04T01:01:44.108383Z", 
      "value": 0.000251, 
      "value.currency": "USD", 
      "when": "8 months ago"
    }, 
    {
      "timestamp": "2017-01-03T01:02:24.694873Z", 
      "value": 0.000286, 
      "value.currency": "USD", 
      "when": "8 months ago"
    }, 
    {
      "timestamp": "2017-01-02T01:02:41.269144Z", 
      "value": 0.000349, 
      "value.currency": "USD", 
      "when": "8 months ago"
    }, 
    {
      "timestamp": "2017-01-01T01:02:39.021170Z", 
      "value": 0.000357, 
      "value.currency": "USD", 
      "when": "8 months ago"
    }, 
    {
      "timestamp": "2016-12-31T01:02:30.228993Z", 
      "value": 0.000356, 
      "value.currency": "USD", 
      "when": "9 months ago"
    }, 
    {
      "timestamp": "2016-12-30T01:02:22.520426Z", 
      "value": 0.00038, 
      "value.currency": "USD", 
      "when": "9 months ago"
    }, 
    {
      "timestamp": "2016-12-29T01:02:19.028143Z", 
      "value": 0.000429, 
      "value.currency": "USD", 
      "when": "9 months ago"
    }, 
    {
      "timestamp": "2016-12-28T01:03:03.663815Z", 
      "value": 0.000429, 
      "value.currency": "USD", 
      "when": "9 months ago"
    }, 
    {
      "timestamp": "2016-12-27T01:02:18.291279Z", 
      "value": 0.000608, 
      "value.currency": "USD", 
      "when": "9 months ago"
    }, 
    {
      "timestamp": "2016-12-26T01:02:13.080184Z", 
      "value": 0.000308, 
      "value.currency": "USD", 
      "when": "9 months ago"
    }, 
    {
      "timestamp": "2016-12-25T01:02:11.261802Z", 
      "value": 0.000386, 
      "value.currency": "USD", 
      "when": "9 months ago"
    }, 
    {
      "timestamp": "2016-12-24T01:02:13.727696Z", 
      "value": 0.000325, 
      "value.currency": "USD", 
      "when": "9 months ago"
    }, 
    {
      "timestamp": "2016-12-23T01:02:57.448101Z", 
      "value": 0.000343, 
      "value.currency": "USD", 
      "when": "9 months ago"
    }, 
    {
      "timestamp": "2016-12-22T01:02:48.711827Z", 
      "value": 0.000676, 
      "value.currency": "USD", 
      "when": "9 months ago"
    }, 
    {
      "timestamp": "2016-12-21T01:02:20.629138Z", 
      "value": 0.000641, 
      "value.currency": "USD", 
      "when": "9 months ago"
    }, 
    {
      "timestamp": "2016-12-20T01:02:34.341185Z", 
      "value": 0.000482, 
      "value.currency": "USD", 
      "when": "9 months ago"
    }, 
    {
      "timestamp": "2016-12-19T01:02:23.160182Z", 
      "value": 0.000624, 
      "value.currency": "USD", 
      "when": "9 months ago"
    }, 
    {
      "timestamp": "2016-12-18T01:02:46.719134Z", 
      "value": 0.00043, 
      "value.currency": "USD", 
      "when": "9 months ago"
    }, 
    {
      "timestamp": "2016-12-17T01:11:55.243598Z", 
      "value": 0.00044, 
      "value.currency": "USD", 
      "when": "9 months ago"
    }, 
    {
      "timestamp": "2016-12-16T01:01:36.022643Z", 
      "value": 0.000505, 
      "value.currency": "USD", 
      "when": "9 months ago"
    }, 
    {
      "timestamp": "2016-12-15T01:01:40.207874Z", 
      "value": 0.000547, 
      "value.currency": "USD", 
      "when": "9 months ago"
    }, 
    {
      "timestamp": "2016-12-14T01:01:29.448847Z", 
      "value": 0.000547, 
      "value.currency": "USD", 
      "when": "9 months ago"
    }, 
    {
      "timestamp": "2016-12-13T01:01:08.445779Z", 
      "value": 0.000562, 
      "value.currency": "USD", 
      "when": "9 months ago"
    }, 
    {
      "timestamp": "2016-12-12T01:01:40.948657Z", 
      "value": 0.000539, 
      "value.currency": "USD", 
      "when": "9 months ago"
    }, 
    {
      "timestamp": "2016-12-11T01:01:22.745011Z", 
      "value": 0.000498, 
      "value.currency": "USD", 
      "when": "9 months ago"
    }, 
    {
      "timestamp": "2016-12-10T01:01:51.040706Z", 
      "value": 0.00059, 
      "value.currency": "USD", 
      "when": "9 months ago"
    }, 
    {
      "timestamp": "2016-12-09T01:01:35.698012Z", 
      "value": 0.00054, 
      "value.currency": "USD", 
      "when": "9 months ago"
    }, 
    {
      "timestamp": "2016-12-08T01:01:20.260329Z", 
      "value": 0.00051, 
      "value.currency": "USD", 
      "when": "9 months ago"
    }, 
    {
      "timestamp": "2016-12-07T01:01:28.674056Z", 
      "value": 0.000808, 
      "value.currency": "USD", 
      "when": "9 months ago"
    }, 
    {
      "timestamp": "2016-12-06T01:01:23.674219Z", 
      "value": 0.000228, 
      "value.currency": "USD", 
      "when": "9 months ago"
    }, 
    {
      "timestamp": "2016-12-05T01:01:50.700870Z", 
      "value": 0.000209, 
      "value.currency": "USD", 
      "when": "9 months ago"
    }, 
    {
      "timestamp": "2016-12-04T01:01:37.913929Z", 
      "value": 0.000183, 
      "value.currency": "USD", 
      "when": "9 months ago"
    }, 
    {
      "timestamp": "2016-12-03T01:01:27.099597Z", 
      "value": 0.000156, 
      "value.currency": "USD", 
      "when": "9 months ago"
    }, 
    {
      "timestamp": "2016-12-02T01:01:26.973552Z", 
      "value": 0.000144, 
      "value.currency": "USD", 
      "when": "9 months ago"
    }, 
    {
      "timestamp": "2016-12-01T01:01:12.682559Z", 
      "value": 0.000142, 
      "value.currency": "USD", 
      "when": "10 months ago"
    }, 
    {
      "timestamp": "2016-11-30T01:01:37.362163Z", 
      "value": 0.000125, 
      "value.currency": "USD", 
      "when": "10 months ago"
    }, 
    {
      "timestamp": "2016-11-29T01:01:51.935483Z", 
      "value": 0.000213, 
      "value.currency": "USD", 
      "when": "10 months ago"
    }, 
    {
      "timestamp": "2016-11-28T01:01:34.132076Z", 
      "value": 0.000176, 
      "value.currency": "USD", 
      "when": "10 months ago"
    }, 
    {
      "timestamp": "2016-11-27T01:01:32.686897Z", 
      "value": 0.000111, 
      "value.currency": "USD", 
      "when": "10 months ago"
    }, 
    {
      "timestamp": "2016-11-26T01:01:16.687827Z", 
      "value": 0.000101, 
      "value.currency": "USD", 
      "when": "10 months ago"
    }, 
    {
      "timestamp": "2016-11-25T01:01:19.828173Z", 
      "value": 0.000141, 
      "value.currency": "USD", 
      "when": "10 months ago"
    }, 
    {
      "timestamp": "2016-11-24T01:01:06.197360Z", 
      "value": 0.000172, 
      "value.currency": "USD", 
      "when": "10 months ago"
    }, 
    {
      "timestamp": "2016-11-23T01:01:28.075808Z", 
      "value": 0.00015, 
      "value.currency": "USD", 
      "when": "10 months ago"
    }, 
    {
      "timestamp": "2016-11-22T01:01:20.887633Z", 
      "value": 0.000218, 
      "value.currency": "USD", 
      "when": "10 months ago"
    }, 
    {
      "timestamp": "2016-11-21T01:01:35.564622Z", 
      "value": 0.000205, 
      "value.currency": "USD", 
      "when": "10 months ago"
    }, 
    {
      "timestamp": "2016-11-20T01:01:25.324148Z", 
      "value": 0.000195, 
      "value.currency": "USD", 
      "when": "10 months ago"
    }, 
    {
      "timestamp": "2016-11-19T01:01:20.067028Z", 
      "value": 0.000278, 
      "value.currency": "USD", 
      "when": "10 months ago"
    }, 
    {
      "timestamp": "2016-11-18T01:01:35.192263Z", 
      "value": 0.000235, 
      "value.currency": "USD", 
      "when": "10 months ago"
    }, 
    {
      "timestamp": "2016-11-17T01:01:48.220589Z", 
      "value": 0.000157, 
      "value.currency": "USD", 
      "when": "10 months ago"
    }, 
    {
      "timestamp": "2016-11-16T01:01:24.967375Z", 
      "value": 0.000185, 
      "value.currency": "USD", 
      "when": "10 months ago"
    }, 
    {
      "timestamp": "2016-11-15T01:01:37.218238Z", 
      "value": 0.00024, 
      "value.currency": "USD", 
      "when": "10 months ago"
    }, 
    {
      "timestamp": "2016-11-14T01:01:10.134540Z", 
      "value": 0.000219, 
      "value.currency": "USD", 
      "when": "10 months ago"
    }, 
    {
      "timestamp": "2016-11-13T01:01:26.811738Z", 
      "value": 0.000275, 
      "value.currency": "USD", 
      "when": "10 months ago"
    }, 
    {
      "timestamp": "2016-11-12T01:01:31.599178Z", 
      "value": 0.000279, 
      "value.currency": "USD", 
      "when": "10 months ago"
    }, 
    {
      "timestamp": "2016-11-11T01:01:39.541145Z", 
      "value": 0.000265, 
      "value.currency": "USD", 
      "when": "10 months ago"
    }, 
    {
      "timestamp": "2016-11-10T01:01:29.745553Z", 
      "value": 0.000485, 
      "value.currency": "USD", 
      "when": "10 months ago"
    }, 
    {
      "timestamp": "2016-11-09T01:01:38.141751Z", 
      "value": 0.000365, 
      "value.currency": "USD", 
      "when": "10 months ago"
    }, 
    {
      "timestamp": "2016-11-08T01:01:25.111372Z", 
      "value": 0.000464, 
      "value.currency": "USD", 
      "when": "10 months ago"
    }, 
    {
      "timestamp": "2016-11-07T01:01:10.269848Z", 
      "value": 0.000562, 
      "value.currency": "USD", 
      "when": "10 months ago"
    }, 
    {
      "timestamp": "2016-11-06T00:01:33.804728Z", 
      "value": 0.000549, 
      "value.currency": "USD", 
      "when": "10 months ago"
    }, 
    {
      "timestamp": "2016-11-05T00:01:31.769530Z", 
      "value": 0.000499, 
      "value.currency": "USD", 
      "when": "10 months ago"
    }, 
    {
      "timestamp": "2016-11-04T00:01:19.438263Z", 
      "value": 0.000668, 
      "value.currency": "USD", 
      "when": "10 months ago"
    }, 
    {
      "timestamp": "2016-11-03T00:01:34.069684Z", 
      "value": 0.000695, 
      "value.currency": "USD", 
      "when": "10 months ago"
    }, 
    {
      "timestamp": "2016-11-02T00:01:10.739103Z", 
      "value": 0.000715, 
      "value.currency": "USD", 
      "when": "10 months ago"
    }, 
    {
      "timestamp": "2016-11-01T00:01:34.396567Z", 
      "value": 0.00075, 
      "value.currency": "USD", 
      "when": "10 months ago"
    }, 
    {
      "timestamp": "2016-10-31T00:01:14.762680Z", 
      "value": 0.000737, 
      "value.currency": "USD", 
      "when": "11 months ago"
    }, 
    {
      "timestamp": "2016-10-30T00:01:16.905308Z", 
      "value": 0.000638, 
      "value.currency": "USD", 
      "when": "11 months ago"
    }, 
    {
      "timestamp": "2016-10-29T00:01:39.064132Z", 
      "value": 0.000621, 
      "value.currency": "USD", 
      "when": "11 months ago"
    }, 
    {
      "timestamp": "2016-10-28T00:01:34.244916Z", 
      "value": 0.000846, 
      "value.currency": "USD", 
      "when": "11 months ago"
    }, 
    {
      "timestamp": "2016-10-27T00:01:01.310290Z", 
      "value": 0.00057, 
      "value.currency": "USD", 
      "when": "11 months ago"
    }, 
    {
      "timestamp": "2016-10-26T00:01:40.985572Z", 
      "value": 0.000789, 
      "value.currency": "USD", 
      "when": "11 months ago"
    }, 
    {
      "timestamp": "2016-10-25T00:01:31.439572Z", 
      "value": 0.000883, 
      "value.currency": "USD", 
      "when": "11 months ago"
    }, 
    {
      "timestamp": "2016-10-24T00:01:35.245074Z", 
      "value": 0.000881, 
      "value.currency": "USD", 
      "when": "11 months ago"
    }, 
    {
      "timestamp": "2016-10-23T00:01:23.263619Z", 
      "value": 0.00088, 
      "value.currency": "USD", 
      "when": "11 months ago"
    }, 
    {
      "timestamp": "2016-10-22T00:01:33.103273Z", 
      "value": 0.000881, 
      "value.currency": "USD", 
      "when": "11 months ago"
    }, 
    {
      "timestamp": "2016-10-21T00:01:07.524534Z", 
      "value": 0.001506, 
      "value.currency": "USD", 
      "when": "11 months ago"
    }, 
    {
      "timestamp": "2016-10-20T00:01:17.151156Z", 
      "value": 0.001136, 
      "value.currency": "USD", 
      "when": "11 months ago"
    }, 
    {
      "timestamp": "2016-10-19T00:01:12.712991Z", 
      "value": 0.001913, 
      "value.currency": "USD", 
      "when": "11 months ago"
    }, 
    {
      "timestamp": "2016-10-18T00:01:22.511464Z", 
      "value": 0.03196, 
      "value.currency": "USD", 
      "when": "11 months ago"
    }, 
    {
      "timestamp": "2016-10-17T00:01:29.205902Z", 
      "value": 0.000949, 
      "value.currency": "USD", 
      "when": "11 months ago"
    }, 
    {
      "timestamp": "2016-10-16T00:01:40.036571Z", 
      "value": 0.000945, 
      "value.currency": "USD", 
      "when": "11 months ago"
    }, 
    {
      "timestamp": "2016-10-15T00:01:21.271218Z", 
      "value": 0.001363, 
      "value.currency": "USD", 
      "when": "11 months ago"
    }, 
    {
      "timestamp": "2016-10-14T00:01:34.113811Z", 
      "value": 0.001324, 
      "value.currency": "USD", 
      "when": "11 months ago"
    }, 
    {
      "timestamp": "2016-10-13T00:01:19.234810Z", 
      "value": 0.001221, 
      "value.currency": "USD", 
      "when": "11 months ago"
    }, 
    {
      "timestamp": "2016-10-12T00:01:46.817677Z", 
      "value": 0.001091, 
      "value.currency": "USD", 
      "when": "11 months ago"
    }, 
    {
      "timestamp": "2016-10-11T00:01:37.051324Z", 
      "value": 0.001479, 
      "value.currency": "USD", 
      "when": "11 months ago"
    }, 
    {
      "timestamp": "2016-10-10T00:01:24.385237Z", 
      "value": 0.001062, 
      "value.currency": "USD", 
      "when": "11 months ago"
    }, 
    {
      "timestamp": "2016-10-09T00:01:25.939990Z", 
      "value": 0.001399, 
      "value.currency": "USD", 
      "when": "11 months ago"
    }, 
    {
      "timestamp": "2016-10-08T00:01:04.579962Z", 
      "value": 0.001382, 
      "value.currency": "USD", 
      "when": "11 months ago"
    }, 
    {
      "timestamp": "2016-10-07T00:01:11.158577Z", 
      "value": 0.001882, 
      "value.currency": "USD", 
      "when": "11 months ago"
    }, 
    {
      "timestamp": "2016-10-06T00:01:23.258691Z", 
      "value": 0.001929, 
      "value.currency": "USD", 
      "when": "11 months ago"
    }, 
    {
      "timestamp": "2016-10-05T00:01:20.810668Z", 
      "value": 0.001416, 
      "value.currency": "USD", 
      "when": "11 months ago"
    }, 
    {
      "timestamp": "2016-10-04T00:01:07.725119Z", 
      "value": 0.001451, 
      "value.currency": "USD", 
      "when": "11 months ago"
    }, 
    {
      "timestamp": "2016-10-03T00:01:20.502947Z", 
      "value": 0.001491, 
      "value.currency": "USD", 
      "when": "11 months ago"
    }, 
    {
      "timestamp": "2016-10-02T00:01:04.198335Z", 
      "value": 0.001418, 
      "value.currency": "USD", 
      "when": "a year ago"
    }, 
    {
      "timestamp": "2016-10-01T00:01:14.740385Z", 
      "value": 0.001402, 
      "value.currency": "USD", 
      "when": "1 year, 1 day ago"
    }, 
    {
      "timestamp": "2016-09-30T00:01:29.939036Z", 
      "value": 0.001587, 
      "value.currency": "USD", 
      "when": "1 year, 2 days ago"
    }, 
    {
      "timestamp": "2016-09-29T00:01:29.965468Z", 
      "value": 0.001988, 
      "value.currency": "USD", 
      "when": "1 year, 3 days ago"
    }, 
    {
      "timestamp": "2016-09-28T00:01:31.807915Z", 
      "value": 0.002121, 
      "value.currency": "USD", 
      "when": "1 year, 4 days ago"
    }, 
    {
      "timestamp": "2016-09-27T00:01:20.552376Z", 
      "value": 0.001326, 
      "value.currency": "USD", 
      "when": "1 year, 5 days ago"
    }, 
    {
      "timestamp": "2016-09-26T00:01:24.037674Z", 
      "value": 0.001238, 
      "value.currency": "USD", 
      "when": "1 year, 6 days ago"
    }, 
    {
      "timestamp": "2016-09-25T00:01:30.555392Z", 
      "value": 0.0018, 
      "value.currency": "USD", 
      "when": "1 year, 7 days ago"
    }, 
    {
      "timestamp": "2016-09-24T00:01:02.058909Z", 
      "value": 0.001212, 
      "value.currency": "USD", 
      "when": "1 year, 8 days ago"
    }, 
    {
      "timestamp": "2016-09-23T00:01:01.425605Z", 
      "value": 0.001281, 
      "value.currency": "USD", 
      "when": "1 year, 9 days ago"
    }, 
    {
      "timestamp": "2016-09-22T00:01:57.665035Z", 
      "value": 0.00117, 
      "value.currency": "USD", 
      "when": "1 year, 10 days ago"
    }, 
    {
      "timestamp": "2016-09-21T00:01:29.699161Z", 
      "value": 0.001218, 
      "value.currency": "USD", 
      "when": "1 year, 11 days ago"
    }, 
    {
      "timestamp": "2016-09-20T00:01:37.856513Z", 
      "value": 0.001407, 
      "value.currency": "USD", 
      "when": "1 year, 12 days ago"
    }, 
    {
      "timestamp": "2016-09-19T00:01:09.985748Z", 
      "value": 0.001281, 
      "value.currency": "USD", 
      "when": "1 year, 13 days ago"
    }, 
    {
      "timestamp": "2016-09-18T00:01:18.890324Z", 
      "value": 0.001346, 
      "value.currency": "USD", 
      "when": "1 year, 14 days ago"
    }, 
    {
      "timestamp": "2016-09-16T00:01:24.342093Z", 
      "value": 0.001326, 
      "value.currency": "USD", 
      "when": "1 year, 16 days ago"
    }, 
    {
      "timestamp": "2016-09-15T00:01:19.369419Z", 
      "value": 0.001331, 
      "value.currency": "USD", 
      "when": "1 year, 17 days ago"
    }, 
    {
      "timestamp": "2016-09-14T00:01:17.494003Z", 
      "value": 0.00166, 
      "value.currency": "USD", 
      "when": "1 year, 18 days ago"
    }, 
    {
      "timestamp": "2016-09-13T00:02:19.794175Z", 
      "value": 0.00138, 
      "value.currency": "USD", 
      "when": "1 year, 19 days ago"
    }, 
    {
      "timestamp": "2016-09-12T00:01:24.706205Z", 
      "value": 0.001528, 
      "value.currency": "USD", 
      "when": "1 year, 20 days ago"
    }, 
    {
      "timestamp": "2016-09-11T00:01:48.289032Z", 
      "value": 0.002361, 
      "value.currency": "USD", 
      "when": "1 year, 21 days ago"
    }, 
    {
      "timestamp": "2016-09-10T00:01:23.888080Z", 
      "value": 0.002067, 
      "value.currency": "USD", 
      "when": "1 year, 22 days ago"
    }, 
    {
      "timestamp": "2016-09-09T00:02:13.019734Z", 
      "value": 0.004224, 
      "value.currency": "USD", 
      "when": "1 year, 23 days ago"
    }, 
    {
      "timestamp": "2016-09-08T00:01:48.463226Z", 
      "value": 0.001498, 
      "value.currency": "USD", 
      "when": "1 year, 24 days ago"
    }, 
    {
      "timestamp": "2016-09-07T00:01:22.351977Z", 
      "value": 0.001599, 
      "value.currency": "USD", 
      "when": "1 year, 25 days ago"
    }, 
    {
      "timestamp": "2016-09-06T00:01:28.438006Z", 
      "value": 0.001933, 
      "value.currency": "USD", 
      "when": "1 year, 26 days ago"
    }, 
    {
      "timestamp": "2016-09-05T00:01:09.301652Z", 
      "value": 0.001945, 
      "value.currency": "USD", 
      "when": "1 year, 27 days ago"
    }, 
    {
      "timestamp": "2016-09-04T00:02:11.284648Z", 
      "value": 0.001912, 
      "value.currency": "USD", 
      "when": "1 year, 28 days ago"
    }, 
    {
      "timestamp": "2016-09-03T00:02:39.177988Z", 
      "value": 0.001214, 
      "value.currency": "USD", 
      "when": "1 year, 29 days ago"
    }, 
    {
      "timestamp": "2016-09-02T00:02:08.889864Z", 
      "value": 0.001883, 
      "value.currency": "USD", 
      "when": "1 year, 30 days ago"
    }, 
    {
      "timestamp": "2016-09-01T00:01:49.297021Z", 
      "value": 0.001385, 
      "value.currency": "USD", 
      "when": "1 year, 1 month ago"
    }, 
    {
      "timestamp": "2016-08-31T00:01:37.373542Z", 
      "value": 0.001723, 
      "value.currency": "USD", 
      "when": "1 year, 1 month ago"
    }, 
    {
      "timestamp": "2016-08-30T00:01:31.035961Z", 
      "value": 0.001701, 
      "value.currency": "USD", 
      "when": "1 year, 1 month ago"
    }, 
    {
      "timestamp": "2016-08-29T00:01:21.642330Z", 
      "value": 0.001785, 
      "value.currency": "USD", 
      "when": "1 year, 1 month ago"
    }, 
    {
      "timestamp": "2016-08-28T00:01:46.801422Z", 
      "value": 0.002006, 
      "value.currency": "USD", 
      "when": "1 year, 1 month ago"
    }, 
    {
      "timestamp": "2016-08-27T00:01:18.979789Z", 
      "value": 0.001866, 
      "value.currency": "USD", 
      "when": "1 year, 1 month ago"
    }, 
    {
      "timestamp": "2016-08-26T00:01:33.700994Z", 
      "value": 0.002352, 
      "value.currency": "USD", 
      "when": "1 year, 1 month ago"
    }, 
    {
      "timestamp": "2016-08-25T00:02:08.287709Z", 
      "value": 0.001682, 
      "value.currency": "USD", 
      "when": "1 year, 1 month ago"
    }, 
    {
      "timestamp": "2016-08-24T00:01:07.191174Z", 
      "value": 0.001605, 
      "value.currency": "USD", 
      "when": "1 year, 1 month ago"
    }, 
    {
      "timestamp": "2016-08-23T00:01:43.463224Z", 
      "value": 0.001187, 
      "value.currency": "USD", 
      "when": "1 year, 1 month ago"
    }, 
    {
      "timestamp": "2016-08-22T00:01:30.800150Z", 
      "value": 0.000977, 
      "value.currency": "USD", 
      "when": "1 year, 1 month ago"
    }, 
    {
      "timestamp": "2016-08-21T00:01:04.919776Z", 
      "value": 0.001732, 
      "value.currency": "USD", 
      "when": "1 year, 1 month ago"
    }, 
    {
      "timestamp": "2016-08-20T00:01:37.609532Z", 
      "value": 0.001581, 
      "value.currency": "USD", 
      "when": "1 year, 1 month ago"
    }, 
    {
      "timestamp": "2016-08-19T00:01:42.456008Z", 
      "value": 0.002205, 
      "value.currency": "USD", 
      "when": "1 year, 1 month ago"
    }, 
    {
      "timestamp": "2016-08-18T00:01:26.450301Z", 
      "value": 0.002113, 
      "value.currency": "USD", 
      "when": "1 year, 1 month ago"
    }, 
    {
      "timestamp": "2016-08-17T00:01:41.219880Z", 
      "value": 0.004529, 
      "value.currency": "USD", 
      "when": "1 year, 1 month ago"
    }, 
    {
      "timestamp": "2016-08-16T00:01:33.967772Z", 
      "value": 0.002427, 
      "value.currency": "USD", 
      "when": "1 year, 1 month ago"
    }, 
    {
      "timestamp": "2016-08-15T00:01:17.366542Z", 
      "value": 0.00471, 
      "value.currency": "USD", 
      "when": "1 year, 1 month ago"
    }, 
    {
      "timestamp": "2016-08-14T00:01:34.057912Z", 
      "value": 0.003525, 
      "value.currency": "USD", 
      "when": "1 year, 1 month ago"
    }, 
    {
      "timestamp": "2016-08-13T00:01:43.396119Z", 
      "value": 0.003526, 
      "value.currency": "USD", 
      "when": "1 year, 1 month ago"
    }, 
    {
      "timestamp": "2016-08-12T00:01:12.015791Z", 
      "value": 0.003955, 
      "value.currency": "USD", 
      "when": "1 year, 1 month ago"
    }, 
    {
      "timestamp": "2016-08-11T00:01:20.856505Z", 
      "value": 0.003786, 
      "value.currency": "USD", 
      "when": "1 year, 1 month ago"
    }, 
    {
      "timestamp": "2016-08-10T00:01:14.417178Z", 
      "value": 0.002983, 
      "value.currency": "USD", 
      "when": "1 year, 1 month ago"
    }, 
    {
      "timestamp": "2016-08-09T00:01:31.932770Z", 
      "value": 0.005841, 
      "value.currency": "USD", 
      "when": "1 year, 1 month ago"
    }, 
    {
      "timestamp": "2016-08-08T00:01:12.125472Z", 
      "value": 0.003801, 
      "value.currency": "USD", 
      "when": "1 year, 1 month ago"
    }, 
    {
      "timestamp": "2016-08-07T00:01:30.161405Z", 
      "value": 0.003976, 
      "value.currency": "USD", 
      "when": "1 year, 1 month ago"
    }, 
    {
      "timestamp": "2016-08-06T00:01:34.584780Z", 
      "value": 0.003827, 
      "value.currency": "USD", 
      "when": "1 year, 1 month ago"
    }, 
    {
      "timestamp": "2016-08-05T00:01:51.554434Z", 
      "value": 0.003643, 
      "value.currency": "USD", 
      "when": "1 year, 1 month ago"
    }, 
    {
      "timestamp": "2016-08-04T00:02:00.816716Z", 
      "value": 0.002413, 
      "value.currency": "USD", 
      "when": "1 year, 1 month ago"
    }, 
    {
      "timestamp": "2016-08-03T00:02:03.318351Z", 
      "value": 0.003623, 
      "value.currency": "USD", 
      "when": "1 year, 1 month ago"
    }, 
    {
      "timestamp": "2016-08-02T00:01:59.622461Z", 
      "value": 0.004296, 
      "value.currency": "USD", 
      "when": "1 year, 2 months ago"
    }, 
    {
      "timestamp": "2016-08-01T00:01:49.232484Z", 
      "value": 0.004525, 
      "value.currency": "USD", 
      "when": "1 year, 2 months ago"
    }, 
    {
      "timestamp": "2016-07-31T00:01:43.729336Z", 
      "value": 0.010938, 
      "value.currency": "USD", 
      "when": "1 year, 2 months ago"
    }, 
    {
      "timestamp": "2016-07-30T00:02:24.310820Z", 
      "value": 0.005023, 
      "value.currency": "USD", 
      "when": "1 year, 2 months ago"
    }, 
    {
      "timestamp": "2016-07-29T00:02:09.902348Z", 
      "value": 0.003407, 
      "value.currency": "USD", 
      "when": "1 year, 2 months ago"
    }, 
    {
      "timestamp": "2016-07-28T00:01:29.295311Z", 
      "value": 0.00265, 
      "value.currency": "USD", 
      "when": "1 year, 2 months ago"
    }, 
    {
      "timestamp": "2016-07-27T00:01:29.577338Z", 
      "value": 0.003539, 
      "value.currency": "USD", 
      "when": "1 year, 2 months ago"
    }, 
    {
      "timestamp": "2016-07-26T00:01:47.585503Z", 
      "value": 0.006328, 
      "value.currency": "USD", 
      "when": "1 year, 2 months ago"
    }, 
    {
      "timestamp": "2016-07-25T00:01:12.435125Z", 
      "value": 0.00769, 
      "value.currency": "USD", 
      "when": "1 year, 2 months ago"
    }, 
    {
      "timestamp": "2016-07-24T00:01:36.742116Z", 
      "value": 0.004556, 
      "value.currency": "USD", 
      "when": "1 year, 2 months ago"
    }, 
    {
      "timestamp": "2016-07-23T00:01:19.326942Z", 
      "value": 0.008297, 
      "value.currency": "USD", 
      "when": "1 year, 2 months ago"
    }, 
    {
      "timestamp": "2016-07-22T00:01:57.094626Z", 
      "value": 0.005661, 
      "value.currency": "USD", 
      "when": "1 year, 2 months ago"
    }, 
    {
      "timestamp": "2016-07-21T00:01:56.325336Z", 
      "value": 0.006589, 
      "value.currency": "USD", 
      "when": "1 year, 2 months ago"
    }, 
    {
      "timestamp": "2016-07-20T00:01:44.116959Z", 
      "value": 0.005354, 
      "value.currency": "USD", 
      "when": "1 year, 2 months ago"
    }, 
    {
      "timestamp": "2016-07-19T00:01:46.671248Z", 
      "value": 0.007339, 
      "value.currency": "USD", 
      "when": "1 year, 2 months ago"
    }, 
    {
      "timestamp": "2016-07-18T00:01:02.168512Z", 
      "value": 0.008289, 
      "value.currency": "USD", 
      "when": "1 year, 2 months ago"
    }, 
    {
      "timestamp": "2016-07-17T00:01:32.492331Z", 
      "value": 0.009761, 
      "value.currency": "USD", 
      "when": "1 year, 2 months ago"
    }, 
    {
      "timestamp": "2016-07-16T00:01:05.738011Z", 
      "value": 0.012441, 
      "value.currency": "USD", 
      "when": "1 year, 2 months ago"
    }, 
    {
      "timestamp": "2016-07-15T00:02:06.204103Z", 
      "value": 0.009242, 
      "value.currency": "USD", 
      "when": "1 year, 2 months ago"
    }, 
    {
      "timestamp": "2016-07-14T00:01:48.785419Z", 
      "value": 0.011002, 
      "value.currency": "USD", 
      "when": "1 year, 2 months ago"
    }, 
    {
      "timestamp": "2016-07-13T00:01:54.380862Z", 
      "value": 0.008639, 
      "value.currency": "USD", 
      "when": "1 year, 2 months ago"
    }, 
    {
      "timestamp": "2016-07-12T00:01:10.162116Z", 
      "value": 0.008157, 
      "value.currency": "USD", 
      "when": "1 year, 2 months ago"
    }, 
    {
      "timestamp": "2016-07-11T00:01:24.622496Z", 
      "value": 0.007725, 
      "value.currency": "USD", 
      "when": "1 year, 2 months ago"
    }, 
    {
      "timestamp": "2016-07-10T00:01:12.542574Z", 
      "value": 0.012602, 
      "value.currency": "USD", 
      "when": "1 year, 2 months ago"
    }, 
    {
      "timestamp": "2016-07-09T00:01:31.521776Z", 
      "value": 0.007354, 
      "value.currency": "USD", 
      "when": "1 year, 2 months ago"
    }, 
    {
      "timestamp": "2016-07-08T00:01:51.120825Z", 
      "value": 0.0128, 
      "value.currency": "USD", 
      "when": "1 year, 2 months ago"
    }, 
    {
      "timestamp": "2016-07-07T00:01:28.937536Z", 
      "value": 0.0135, 
      "value.currency": "USD", 
      "when": "1 year, 2 months ago"
    }, 
    {
      "timestamp": "2016-07-06T00:01:00.132187Z", 
      "value": 0.009937, 
      "value.currency": "USD", 
      "when": "1 year, 2 months ago"
    }, 
    {
      "timestamp": "2016-07-05T00:01:39.548868Z", 
      "value": 0.009405, 
      "value.currency": "USD", 
      "when": "1 year, 2 months ago"
    }, 
    {
      "timestamp": "2016-07-04T00:01:53.138073Z", 
      "value": 0.00649, 
      "value.currency": "USD", 
      "when": "1 year, 2 months ago"
    }, 
    {
      "timestamp": "2016-07-03T00:01:56.990374Z", 
      "value": 0.005248, 
      "value.currency": "USD", 
      "when": "1 year, 2 months ago"
    }, 
    {
      "timestamp": "2016-07-02T00:01:57.427469Z", 
      "value": 0.005364, 
      "value.currency": "USD", 
      "when": "1 year, 3 months ago"
    }, 
    {
      "timestamp": "2016-07-01T00:01:56.964502Z", 
      "value": 0.00285, 
      "value.currency": "USD", 
      "when": "1 year, 3 months ago"
    }, 
    {
      "timestamp": "2016-06-30T00:00:59.111210Z", 
      "value": 0.005703, 
      "value.currency": "USD", 
      "when": "1 year, 3 months ago"
    }, 
    {
      "timestamp": "2016-06-29T00:01:35.105923Z", 
      "value": 0.005764, 
      "value.currency": "USD", 
      "when": "1 year, 3 months ago"
    }, 
    {
      "timestamp": "2016-06-28T00:01:44.608479Z", 
      "value": 0.005596, 
      "value.currency": "USD", 
      "when": "1 year, 3 months ago"
    }, 
    {
      "timestamp": "2016-06-27T00:01:16.715175Z", 
      "value": 0.002747, 
      "value.currency": "USD", 
      "when": "1 year, 3 months ago"
    }, 
    {
      "timestamp": "2016-06-25T00:01:24.762344Z", 
      "value": 0.004192, 
      "value.currency": "USD", 
      "when": "1 year, 3 months ago"
    }, 
    {
      "timestamp": "2016-06-24T00:01:13.773004Z", 
      "value": 0.004024, 
      "value.currency": "USD", 
      "when": "1 year, 3 months ago"
    }, 
    {
      "timestamp": "2016-06-23T00:01:46.232369Z", 
      "value": 0.004525, 
      "value.currency": "USD", 
      "when": "1 year, 3 months ago"
    }, 
    {
      "timestamp": "2016-06-22T00:01:43.674453Z", 
      "value": 0.005241, 
      "value.currency": "USD", 
      "when": "1 year, 3 months ago"
    }, 
    {
      "timestamp": "2016-06-20T00:01:52.467503Z", 
      "value": 0.007246, 
      "value.currency": "USD", 
      "when": "1 year, 3 months ago"
    }, 
    {
      "timestamp": "2016-06-19T00:01:11.111231Z", 
      "value": 0.007194, 
      "value.currency": "USD", 
      "when": "1 year, 3 months ago"
    }, 
    {
      "timestamp": "2016-06-18T00:01:52.504471Z", 
      "value": 0.007126, 
      "value.currency": "USD", 
      "when": "1 year, 3 months ago"
    }, 
    {
      "timestamp": "2016-06-17T00:01:17.524221Z", 
      "value": 0.007278, 
      "value.currency": "USD", 
      "when": "1 year, 3 months ago"
    }, 
    {
      "timestamp": "2016-06-16T00:01:51.467249Z", 
      "value": 0.006154, 
      "value.currency": "USD", 
      "when": "1 year, 3 months ago"
    }, 
    {
      "timestamp": "2016-06-15T00:01:26.308078Z", 
      "value": 0.011459, 
      "value.currency": "USD", 
      "when": "1 year, 3 months ago"
    }, 
    {
      "timestamp": "2016-06-13T00:01:17.254857Z", 
      "value": 0.007513, 
      "value.currency": "USD", 
      "when": "1 year, 3 months ago"
    }, 
    {
      "timestamp": "2016-06-12T00:01:30.586014Z", 
      "value": 0.007225, 
      "value.currency": "USD", 
      "when": "1 year, 3 months ago"
    }, 
    {
      "timestamp": "2016-06-11T00:01:16.751500Z", 
      "value": 0.008537, 
      "value.currency": "USD", 
      "when": "1 year, 3 months ago"
    }, 
    {
      "timestamp": "2016-06-10T00:01:27.611599Z", 
      "value": 0.006149, 
      "value.currency": "USD", 
      "when": "1 year, 3 months ago"
    }, 
    {
      "timestamp": "2016-06-09T00:01:27.869799Z", 
      "value": 0.005987, 
      "value.currency": "USD", 
      "when": "1 year, 3 months ago"
    }, 
    {
      "timestamp": "2016-06-08T00:02:01.446718Z", 
      "value": 0.006433, 
      "value.currency": "USD", 
      "when": "1 year, 3 months ago"
    }, 
    {
      "timestamp": "2016-06-07T00:02:07.628105Z", 
      "value": 0.007439, 
      "value.currency": "USD", 
      "when": "1 year, 3 months ago"
    }, 
    {
      "timestamp": "2016-06-06T00:01:49.324480Z", 
      "value": 0.007316, 
      "value.currency": "USD", 
      "when": "1 year, 3 months ago"
    }, 
    {
      "timestamp": "2016-06-05T00:01:21.874278Z", 
      "value": 0.008598, 
      "value.currency": "USD", 
      "when": "1 year, 3 months ago"
    }, 
    {
      "timestamp": "2016-06-04T00:01:16.431243Z", 
      "value": 0.009281, 
      "value.currency": "USD", 
      "when": "1 year, 3 months ago"
    }, 
    {
      "timestamp": "2016-06-03T00:01:46.976799Z", 
      "value": 0.009157, 
      "value.currency": "USD", 
      "when": "1 year, 3 months ago"
    }, 
    {
      "timestamp": "2016-06-02T00:01:55.183776Z", 
      "value": 0.009114, 
      "value.currency": "USD", 
      "when": "1 year, 4 months ago"
    }, 
    {
      "timestamp": "2016-06-01T00:01:29.395315Z", 
      "value": 0.009569, 
      "value.currency": "USD", 
      "when": "1 year, 4 months ago"
    }, 
    {
      "timestamp": "2016-05-31T00:01:38.018858Z", 
      "value": 0.009, 
      "value.currency": "USD", 
      "when": "1 year, 4 months ago"
    }, 
    {
      "timestamp": "2016-05-30T00:01:24.979599Z", 
      "value": 0.010538, 
      "value.currency": "USD", 
      "when": "1 year, 4 months ago"
    }, 
    {
      "timestamp": "2016-05-29T00:01:17.869261Z", 
      "value": 0.009487, 
      "value.currency": "USD", 
      "when": "1 year, 4 months ago"
    }, 
    {
      "timestamp": "2016-05-28T00:01:34.281928Z", 
      "value": 0.008697, 
      "value.currency": "USD", 
      "when": "1 year, 4 months ago"
    }, 
    {
      "timestamp": "2016-05-27T00:01:57.470890Z", 
      "value": 0.009221, 
      "value.currency": "USD", 
      "when": "1 year, 4 months ago"
    }, 
    {
      "timestamp": "2016-05-26T00:01:23.627990Z", 
      "value": 0.008645, 
      "value.currency": "USD", 
      "when": "1 year, 4 months ago"
    }, 
    {
      "timestamp": "2016-05-25T00:01:39.834161Z", 
      "value": 0.01114, 
      "value.currency": "USD", 
      "when": "1 year, 4 months ago"
    }, 
    {
      "timestamp": "2016-05-24T00:02:14.178731Z", 
      "value": 0.009007, 
      "value.currency": "USD", 
      "when": "1 year, 4 months ago"
    }, 
    {
      "timestamp": "2016-05-23T00:01:54.059287Z", 
      "value": 0.009211, 
      "value.currency": "USD", 
      "when": "1 year, 4 months ago"
    }, 
    {
      "timestamp": "2016-05-22T00:01:19.421356Z", 
      "value": 0.008018, 
      "value.currency": "USD", 
      "when": "1 year, 4 months ago"
    }, 
    {
      "timestamp": "2016-05-21T00:01:44.302554Z", 
      "value": 0.009681, 
      "value.currency": "USD", 
      "when": "1 year, 4 months ago"
    }, 
    {
      "timestamp": "2016-05-20T00:01:46.793599Z", 
      "value": 0.009669, 
      "value.currency": "USD", 
      "when": "1 year, 4 months ago"
    }, 
    {
      "timestamp": "2016-05-19T00:01:09.640413Z", 
      "value": 0.009994, 
      "value.currency": "USD", 
      "when": "1 year, 4 months ago"
    }, 
    {
      "timestamp": "2016-05-18T00:01:37.166371Z", 
      "value": 0.010023, 
      "value.currency": "USD", 
      "when": "1 year, 4 months ago"
    }, 
    {
      "timestamp": "2016-05-17T00:01:52.482072Z", 
      "value": 0.010743, 
      "value.currency": "USD", 
      "when": "1 year, 4 months ago"
    }, 
    {
      "timestamp": "2016-05-16T00:01:36.735768Z", 
      "value": 0.012388, 
      "value.currency": "USD", 
      "when": "1 year, 4 months ago"
    }, 
    {
      "timestamp": "2016-05-15T00:01:42.309417Z", 
      "value": 0.014437, 
      "value.currency": "USD", 
      "when": "1 year, 4 months ago"
    }, 
    {
      "timestamp": "2016-05-14T00:01:47.070847Z", 
      "value": 0.007842, 
      "value.currency": "USD", 
      "when": "1 year, 4 months ago"
    }, 
    {
      "timestamp": "2016-05-13T00:01:33.558589Z", 
      "value": 0.008963, 
      "value.currency": "USD", 
      "when": "1 year, 4 months ago"
    }, 
    {
      "timestamp": "2016-05-12T00:01:49.862226Z", 
      "value": 0.010013, 
      "value.currency": "USD", 
      "when": "1 year, 4 months ago"
    }, 
    {
      "timestamp": "2016-05-11T00:01:11.734078Z", 
      "value": 0.010673, 
      "value.currency": "USD", 
      "when": "1 year, 4 months ago"
    }, 
    {
      "timestamp": "2016-05-10T00:01:26.740335Z", 
      "value": 0.009472, 
      "value.currency": "USD", 
      "when": "1 year, 4 months ago"
    }, 
    {
      "timestamp": "2016-05-09T00:00:55.944757Z", 
      "value": 0.009423, 
      "value.currency": "USD", 
      "when": "1 year, 4 months ago"
    }, 
    {
      "timestamp": "2016-05-08T00:02:07.639857Z", 
      "value": 0.009432, 
      "value.currency": "USD", 
      "when": "1 year, 4 months ago"
    }, 
    {
      "timestamp": "2016-05-07T00:01:09.653914Z", 
      "value": 0.009339, 
      "value.currency": "USD", 
      "when": "1 year, 4 months ago"
    }, 
    {
      "timestamp": "2016-05-06T00:02:13.885419Z", 
      "value": 0.009022, 
      "value.currency": "USD", 
      "when": "1 year, 4 months ago"
    }, 
    {
      "timestamp": "2016-05-05T00:01:56.157192Z", 
      "value": 0.008631, 
      "value.currency": "USD", 
      "when": "1 year, 4 months ago"
    }, 
    {
      "timestamp": "2016-05-04T00:01:15.231123Z", 
      "value": 0.009124, 
      "value.currency": "USD", 
      "when": "1 year, 4 months ago"
    }, 
    {
      "timestamp": "2016-05-03T00:01:44.073842Z", 
      "value": 0.00901, 
      "value.currency": "USD", 
      "when": "1 year, 4 months ago"
    }, 
    {
      "timestamp": "2016-05-02T00:01:28.923198Z", 
      "value": 0.009024, 
      "value.currency": "USD", 
      "when": "1 year, 5 months ago"
    }, 
    {
      "timestamp": "2016-05-01T00:01:29.678206Z", 
      "value": 0.009054, 
      "value.currency": "USD", 
      "when": "1 year, 5 months ago"
    }, 
    {
      "timestamp": "2016-04-30T00:01:47.937631Z", 
      "value": 0.009056, 
      "value.currency": "USD", 
      "when": "1 year, 5 months ago"
    }, 
    {
      "timestamp": "2016-04-29T00:02:39.642328Z", 
      "value": 0.00904, 
      "value.currency": "USD", 
      "when": "1 year, 5 months ago"
    }, 
    {
      "timestamp": "2016-04-28T00:02:52.303508Z", 
      "value": 0.009076, 
      "value.currency": "USD", 
      "when": "1 year, 5 months ago"
    }, 
    {
      "timestamp": "2016-04-27T00:02:10.857403Z", 
      "value": 0.009322, 
      "value.currency": "USD", 
      "when": "1 year, 5 months ago"
    }, 
    {
      "timestamp": "2016-04-26T00:01:59.361361Z", 
      "value": 0.009265, 
      "value.currency": "USD", 
      "when": "1 year, 5 months ago"
    }, 
    {
      "timestamp": "2016-04-25T00:01:37.960966Z", 
      "value": 0.009437, 
      "value.currency": "USD", 
      "when": "1 year, 5 months ago"
    }, 
    {
      "timestamp": "2016-04-24T00:01:26.259748Z", 
      "value": 0.009285, 
      "value.currency": "USD", 
      "when": "1 year, 5 months ago"
    }, 
    {
      "timestamp": "2016-04-23T00:01:46.306633Z", 
      "value": 0.008077, 
      "value.currency": "USD", 
      "when": "1 year, 5 months ago"
    }, 
    {
      "timestamp": "2016-04-22T00:02:21.708154Z", 
      "value": 0.009353, 
      "value.currency": "USD", 
      "when": "1 year, 5 months ago"
    }, 
    {
      "timestamp": "2016-04-21T00:01:22.113449Z", 
      "value": 0.0096, 
      "value.currency": "USD", 
      "when": "1 year, 5 months ago"
    }, 
    {
      "timestamp": "2016-04-20T00:02:20.824821Z", 
      "value": 0.008929, 
      "value.currency": "USD", 
      "when": "1 year, 5 months ago"
    }, 
    {
      "timestamp": "2016-04-19T00:02:17.929253Z", 
      "value": 0.008679, 
      "value.currency": "USD", 
      "when": "1 year, 5 months ago"
    }, 
    {
      "timestamp": "2016-04-18T00:01:29.517505Z", 
      "value": 0.008663, 
      "value.currency": "USD", 
      "when": "1 year, 5 months ago"
    }, 
    {
      "timestamp": "2016-04-17T00:01:30.508564Z", 
      "value": 0.007733, 
      "value.currency": "USD", 
      "when": "1 year, 5 months ago"
    }, 
    {
      "timestamp": "2016-04-16T00:01:36.281300Z", 
      "value": 0.008276, 
      "value.currency": "USD", 
      "when": "1 year, 5 months ago"
    }, 
    {
      "timestamp": "2016-04-15T00:02:01.207622Z", 
      "value": 0.009699, 
      "value.currency": "USD", 
      "when": "1 year, 5 months ago"
    }, 
    {
      "timestamp": "2016-04-14T00:02:17.152475Z", 
      "value": 0.009737, 
      "value.currency": "USD", 
      "when": "1 year, 5 months ago"
    }, 
    {
      "timestamp": "2016-04-13T00:01:15.662091Z", 
      "value": 0.009767, 
      "value.currency": "USD", 
      "when": "1 year, 5 months ago"
    }, 
    {
      "timestamp": "2016-04-12T00:01:45.279562Z", 
      "value": 0.007457, 
      "value.currency": "USD", 
      "when": "1 year, 5 months ago"
    }, 
    {
      "timestamp": "2016-04-11T00:01:16.354371Z", 
      "value": 0.008001, 
      "value.currency": "USD", 
      "when": "1 year, 5 months ago"
    }, 
    {
      "timestamp": "2016-04-10T00:01:43.327624Z", 
      "value": 0.008225, 
      "value.currency": "USD", 
      "when": "1 year, 5 months ago"
    }, 
    {
      "timestamp": "2016-04-09T00:01:23.334747Z", 
      "value": 0.008092, 
      "value.currency": "USD", 
      "when": "1 year, 5 months ago"
    }, 
    {
      "timestamp": "2016-04-08T00:01:39.119053Z", 
      "value": 0.00873, 
      "value.currency": "USD", 
      "when": "1 year, 5 months ago"
    }, 
    {
      "timestamp": "2016-04-07T00:02:01.467037Z", 
      "value": 0.009285, 
      "value.currency": "USD", 
      "when": "1 year, 5 months ago"
    }, 
    {
      "timestamp": "2016-04-06T00:01:51.177692Z", 
      "value": 0.009914, 
      "value.currency": "USD", 
      "when": "1 year, 5 months ago"
    }, 
    {
      "timestamp": "2016-04-05T00:01:49.135860Z", 
      "value": 0.009693, 
      "value.currency": "USD", 
      "when": "1 year, 5 months ago"
    }, 
    {
      "timestamp": "2016-04-04T00:01:35.769748Z", 
      "value": 0.009887, 
      "value.currency": "USD", 
      "when": "1 year, 5 months ago"
    }, 
    {
      "timestamp": "2016-04-03T00:01:33.964559Z", 
      "value": 0.009094, 
      "value.currency": "USD", 
      "when": "1 year, 5 months ago"
    }, 
    {
      "timestamp": "2016-04-02T00:01:46.479702Z", 
      "value": 0.009287, 
      "value.currency": "USD", 
      "when": "1 year, 6 months ago"
    }, 
    {
      "timestamp": "2016-04-01T00:01:36.498455Z", 
      "value": 0.010397, 
      "value.currency": "USD", 
      "when": "1 year, 6 months ago"
    }, 
    {
      "timestamp": "2016-03-31T00:01:32.249946Z", 
      "value": 0.010785, 
      "value.currency": "USD", 
      "when": "1 year, 6 months ago"
    }, 
    {
      "timestamp": "2016-03-30T00:01:03.333831Z", 
      "value": 0.010829, 
      "value.currency": "USD", 
      "when": "1 year, 6 months ago"
    }, 
    {
      "timestamp": "2016-03-29T00:02:05.424766Z", 
      "value": 0.009897, 
      "value.currency": "USD", 
      "when": "1 year, 6 months ago"
    }, 
    {
      "timestamp": "2016-03-28T00:01:47.384434Z", 
      "value": 0.010545, 
      "value.currency": "USD", 
      "when": "1 year, 6 months ago"
    }, 
    {
      "timestamp": "2016-03-27T00:02:15.781449Z", 
      "value": 0.008392, 
      "value.currency": "USD", 
      "when": "1 year, 6 months ago"
    }, 
    {
      "timestamp": "2016-03-26T00:01:02.431704Z", 
      "value": 0.007927, 
      "value.currency": "USD", 
      "when": "1 year, 6 months ago"
    }, 
    {
      "timestamp": "2016-03-25T00:00:53.651238Z", 
      "value": 0.010143, 
      "value.currency": "USD", 
      "when": "1 year, 6 months ago"
    }, 
    {
      "timestamp": "2016-03-24T00:01:41.369073Z", 
      "value": 0.014882, 
      "value.currency": "USD", 
      "when": "1 year, 6 months ago"
    }, 
    {
      "timestamp": "2016-03-23T00:02:05.421147Z", 
      "value": 0.012961, 
      "value.currency": "USD", 
      "when": "1 year, 6 months ago"
    }, 
    {
      "timestamp": "2016-03-22T00:02:02.342915Z", 
      "value": 0.009006, 
      "value.currency": "USD", 
      "when": "1 year, 6 months ago"
    }, 
    {
      "timestamp": "2016-03-21T00:00:59.345567Z", 
      "value": 0.012413, 
      "value.currency": "USD", 
      "when": "1 year, 6 months ago"
    }, 
    {
      "timestamp": "2016-03-20T00:01:35.178408Z", 
      "value": 0.005664, 
      "value.currency": "USD", 
      "when": "1 year, 6 months ago"
    }, 
    {
      "timestamp": "2016-03-19T00:02:05.752474Z", 
      "value": 0.006401, 
      "value.currency": "USD", 
      "when": "1 year, 6 months ago"
    }, 
    {
      "timestamp": "2016-03-18T00:01:28.523884Z", 
      "value": 0.008833, 
      "value.currency": "USD", 
      "when": "1 year, 6 months ago"
    }, 
    {
      "timestamp": "2016-03-17T00:01:42.738258Z", 
      "value": 0.010421, 
      "value.currency": "USD", 
      "when": "1 year, 6 months ago"
    }, 
    {
      "timestamp": "2016-03-16T00:02:29.951183Z", 
      "value": 0.010421, 
      "value.currency": "USD", 
      "when": "1 year, 6 months ago"
    }, 
    {
      "timestamp": "2016-03-15T00:01:22.713675Z", 
      "value": 0.012493, 
      "value.currency": "USD", 
      "when": "1 year, 6 months ago"
    }, 
    {
      "timestamp": "2016-03-14T00:01:37.259254Z", 
      "value": 0.013246, 
      "value.currency": "USD", 
      "when": "1 year, 6 months ago"
    }, 
    {
      "timestamp": "2016-03-13T01:01:18.667347Z", 
      "value": 0.008241, 
      "value.currency": "USD", 
      "when": "1 year, 6 months ago"
    }, 
    {
      "timestamp": "2016-03-12T01:01:18.566960Z", 
      "value": 0.022493, 
      "value.currency": "USD", 
      "when": "1 year, 6 months ago"
    }, 
    {
      "timestamp": "2016-03-11T01:01:09.384294Z", 
      "value": 0.010424, 
      "value.currency": "USD", 
      "when": "1 year, 6 months ago"
    }, 
    {
      "timestamp": "2016-03-10T01:01:05.608789Z", 
      "value": 0.007368, 
      "value.currency": "USD", 
      "when": "1 year, 6 months ago"
    }, 
    {
      "timestamp": "2016-03-09T01:01:17.807887Z", 
      "value": 0.005903, 
      "value.currency": "USD", 
      "when": "1 year, 6 months ago"
    }, 
    {
      "timestamp": "2016-03-08T01:00:57.118593Z", 
      "value": 0.007251, 
      "value.currency": "USD", 
      "when": "1 year, 6 months ago"
    }, 
    {
      "timestamp": "2016-03-07T01:00:44.783046Z", 
      "value": 0.007828, 
      "value.currency": "USD", 
      "when": "1 year, 6 months ago"
    }, 
    {
      "timestamp": "2016-03-06T01:00:39.876064Z", 
      "value": 0.007667, 
      "value.currency": "USD", 
      "when": "1 year, 6 months ago"
    }, 
    {
      "timestamp": "2016-03-05T01:00:55.848093Z", 
      "value": 0.008231, 
      "value.currency": "USD", 
      "when": "1 year, 6 months ago"
    }, 
    {
      "timestamp": "2016-03-04T01:01:11.636483Z", 
      "value": 0.008441, 
      "value.currency": "USD", 
      "when": "1 year, 6 months ago"
    }, 
    {
      "timestamp": "2016-03-03T01:06:17.940832Z", 
      "value": 0.007109, 
      "value.currency": "USD", 
      "when": "1 year, 6 months ago"
    }, 
    {
      "timestamp": "2016-03-02T01:01:11.073444Z", 
      "value": 0.008698, 
      "value.currency": "USD", 
      "when": "1 year, 7 months ago"
    }, 
    {
      "timestamp": "2016-03-01T01:00:40.627244Z", 
      "value": 0.010019, 
      "value.currency": "USD", 
      "when": "1 year, 7 months ago"
    }, 
    {
      "timestamp": "2016-02-29T01:00:35.109220Z", 
      "value": 0.009092, 
      "value.currency": "USD", 
      "when": "1 year, 7 months ago"
    }, 
    {
      "timestamp": "2016-02-28T01:00:56.785728Z", 
      "value": 0.009507, 
      "value.currency": "USD", 
      "when": "1 year, 7 months ago"
    }, 
    {
      "timestamp": "2016-02-27T01:00:56.629759Z", 
      "value": 0.008457, 
      "value.currency": "USD", 
      "when": "1 year, 7 months ago"
    }, 
    {
      "timestamp": "2016-02-26T01:00:48.345676Z", 
      "value": 0.009765, 
      "value.currency": "USD", 
      "when": "1 year, 7 months ago"
    }, 
    {
      "timestamp": "2016-02-25T01:00:41.181014Z", 
      "value": 0.021214, 
      "value.currency": "USD", 
      "when": "1 year, 7 months ago"
    }, 
    {
      "timestamp": "2016-02-24T01:01:22.260312Z", 
      "value": 0.012626, 
      "value.currency": "USD", 
      "when": "1 year, 7 months ago"
    }, 
    {
      "timestamp": "2016-02-23T01:01:09.019838Z", 
      "value": 0.017488, 
      "value.currency": "USD", 
      "when": "1 year, 7 months ago"
    }, 
    {
      "timestamp": "2016-02-22T01:00:50.372214Z", 
      "value": 0.019303, 
      "value.currency": "USD", 
      "when": "1 year, 7 months ago"
    }, 
    {
      "timestamp": "2016-02-21T01:00:32.155051Z", 
      "value": 0.012682, 
      "value.currency": "USD", 
      "when": "1 year, 7 months ago"
    }, 
    {
      "timestamp": "2016-02-20T01:00:34.866325Z", 
      "value": 0.016621, 
      "value.currency": "USD", 
      "when": "1 year, 7 months ago"
    }, 
    {
      "timestamp": "2016-02-19T01:01:12.540525Z", 
      "value": 0.03379, 
      "value.currency": "USD", 
      "when": "1 year, 7 months ago"
    }, 
    {
      "timestamp": "2016-02-18T01:01:32.041353Z", 
      "value": 0.03331, 
      "value.currency": "USD", 
      "when": "1 year, 7 months ago"
    }, 
    {
      "timestamp": "2016-02-17T01:01:28.507909Z", 
      "value": 0.052953, 
      "value.currency": "USD", 
      "when": "1 year, 7 months ago"
    }, 
    {
      "timestamp": "2016-02-16T01:01:22.592174Z", 
      "value": 0.037613, 
      "value.currency": "USD", 
      "when": "1 year, 7 months ago"
    }, 
    {
      "timestamp": "2016-02-15T01:01:24.424679Z", 
      "value": 0.038373, 
      "value.currency": "USD", 
      "when": "1 year, 7 months ago"
    }, 
    {
      "timestamp": "2016-02-14T01:01:59.641902Z", 
      "value": 0.058701, 
      "value.currency": "USD", 
      "when": "1 year, 7 months ago"
    }, 
    {
      "timestamp": "2016-02-13T01:00:58.349306Z", 
      "value": 0.060425, 
      "value.currency": "USD", 
      "when": "1 year, 7 months ago"
    }, 
    {
      "timestamp": "2016-02-12T01:01:22.146462Z", 
      "value": 0.045559, 
      "value.currency": "USD", 
      "when": "1 year, 7 months ago"
    }, 
    {
      "timestamp": "2016-02-11T01:00:54.513382Z", 
      "value": 0.06101, 
      "value.currency": "USD", 
      "when": "1 year, 7 months ago"
    }, 
    {
      "timestamp": "2016-02-10T01:01:14.817022Z", 
      "value": 0.05452, 
      "value.currency": "USD", 
      "when": "1 year, 7 months ago"
    }, 
    {
      "timestamp": "2016-02-09T01:00:59.759617Z", 
      "value": 0.045266, 
      "value.currency": "USD", 
      "when": "1 year, 7 months ago"
    }, 
    {
      "timestamp": "2016-02-08T01:01:00.951498Z", 
      "value": 0.053235, 
      "value.currency": "USD", 
      "when": "1 year, 7 months ago"
    }, 
    {
      "timestamp": "2016-02-07T01:00:56.185239Z", 
      "value": 0.05495, 
      "value.currency": "USD", 
      "when": "1 year, 7 months ago"
    }, 
    {
      "timestamp": "2016-02-06T01:01:14.754877Z", 
      "value": 0.05068, 
      "value.currency": "USD", 
      "when": "1 year, 7 months ago"
    }, 
    {
      "timestamp": "2016-02-05T01:01:25.342139Z", 
      "value": 0.058396, 
      "value.currency": "USD", 
      "when": "1 year, 7 months ago"
    }, 
    {
      "timestamp": "2016-02-04T01:00:55.615712Z", 
      "value": 0.048101, 
      "value.currency": "USD", 
      "when": "1 year, 7 months ago"
    }, 
    {
      "timestamp": "2016-02-03T01:01:16.784109Z", 
      "value": 0.057691, 
      "value.currency": "USD", 
      "when": "1 year, 7 months ago"
    }, 
    {
      "timestamp": "2016-02-02T01:01:20.414780Z", 
      "value": 0.055996, 
      "value.currency": "USD", 
      "when": "1 year, 7 months ago"
    }, 
    {
      "timestamp": "2016-02-01T01:02:02.586763Z", 
      "value": 0.058634, 
      "value.currency": "USD", 
      "when": "1 year, 8 months ago"
    }, 
    {
      "timestamp": "2016-01-31T01:01:34.351386Z", 
      "value": 0.052907, 
      "value.currency": "USD", 
      "when": "1 year, 8 months ago"
    }, 
    {
      "timestamp": "2016-01-30T01:01:24.321349Z", 
      "value": 0.05878, 
      "value.currency": "USD", 
      "when": "1 year, 8 months ago"
    }, 
    {
      "timestamp": "2016-01-29T01:01:02.025477Z", 
      "value": 0.062748, 
      "value.currency": "USD", 
      "when": "1 year, 8 months ago"
    }, 
    {
      "timestamp": "2016-01-28T01:01:04.475868Z", 
      "value": 0.063219, 
      "value.currency": "USD", 
      "when": "1 year, 8 months ago"
    }, 
    {
      "timestamp": "2016-01-27T01:01:11.538200Z", 
      "value": 0.066509, 
      "value.currency": "USD", 
      "when": "1 year, 8 months ago"
    }, 
    {
      "timestamp": "2016-01-26T01:00:44.473407Z", 
      "value": 0.066445, 
      "value.currency": "USD", 
      "when": "1 year, 8 months ago"
    }, 
    {
      "timestamp": "2016-01-25T01:00:49.388606Z", 
      "value": 0.057593, 
      "value.currency": "USD", 
      "when": "1 year, 8 months ago"
    }, 
    {
      "timestamp": "2016-01-24T01:13:32.879344Z", 
      "value": 0.060108, 
      "value.currency": "USD", 
      "when": "1 year, 8 months ago"
    }
  ]
}
