{
  "history": [
    {
      "timestamp": "2017-10-02T00:00:44.174983Z", 
      "value": 0.036677, 
      "value.currency": "USD", 
      "when": "18 hours ago"
    }, 
    {
      "timestamp": "2017-10-01T00:01:24.134543Z", 
      "value": 0.104097, 
      "value.currency": "USD", 
      "when": "a day ago"
    }, 
    {
      "timestamp": "2017-09-30T00:01:03.122059Z", 
      "value": 0.037284, 
      "value.currency": "USD", 
      "when": "2 days ago"
    }, 
    {
      "timestamp": "2017-09-29T00:01:07.693446Z", 
      "value": 0.030175, 
      "value.currency": "USD", 
      "when": "3 days ago"
    }, 
    {
      "timestamp": "2017-09-28T00:01:07.197467Z", 
      "value": 0.02192, 
      "value.currency": "USD", 
      "when": "4 days ago"
    }, 
    {
      "timestamp": "2017-09-27T00:00:31.665558Z", 
      "value": 0.028856, 
      "value.currency": "USD", 
      "when": "5 days ago"
    }, 
    {
      "timestamp": "2017-09-26T00:00:40.180826Z", 
      "value": 0.023602, 
      "value.currency": "USD", 
      "when": "6 days ago"
    }, 
    {
      "timestamp": "2017-09-25T00:00:38.213611Z", 
      "value": 0.022057, 
      "value.currency": "USD", 
      "when": "7 days ago"
    }, 
    {
      "timestamp": "2017-09-24T00:01:09.737975Z", 
      "value": 0.022922, 
      "value.currency": "USD", 
      "when": "8 days ago"
    }, 
    {
      "timestamp": "2017-09-23T00:01:05.218218Z", 
      "value": 0.019319, 
      "value.currency": "USD", 
      "when": "9 days ago"
    }, 
    {
      "timestamp": "2017-09-21T00:01:04.539703Z", 
      "value": 0.024058, 
      "value.currency": "USD", 
      "when": "11 days ago"
    }, 
    {
      "timestamp": "2017-09-20T00:00:54.010581Z", 
      "value": 0.023513, 
      "value.currency": "USD", 
      "when": "12 days ago"
    }, 
    {
      "timestamp": "2017-09-19T00:00:53.923939Z", 
      "value": 0.024559, 
      "value.currency": "USD", 
      "when": "13 days ago"
    }, 
    {
      "timestamp": "2017-09-18T00:00:40.153803Z", 
      "value": 0.02297, 
      "value.currency": "USD", 
      "when": "14 days ago"
    }, 
    {
      "timestamp": "2017-09-17T00:00:56.103266Z", 
      "value": 0.023082, 
      "value.currency": "USD", 
      "when": "15 days ago"
    }, 
    {
      "timestamp": "2017-09-16T00:00:54.014401Z", 
      "value": 0.031463, 
      "value.currency": "USD", 
      "when": "16 days ago"
    }, 
    {
      "timestamp": "2017-09-15T00:00:56.749266Z", 
      "value": 0.025756, 
      "value.currency": "USD", 
      "when": "17 days ago"
    }, 
    {
      "timestamp": "2017-09-14T00:01:20.803742Z", 
      "value": 0.031019, 
      "value.currency": "USD", 
      "when": "18 days ago"
    }, 
    {
      "timestamp": "2017-09-13T00:00:52.037998Z", 
      "value": 0.032385, 
      "value.currency": "USD", 
      "when": "19 days ago"
    }, 
    {
      "timestamp": "2017-09-12T00:00:57.382724Z", 
      "value": 0.033688, 
      "value.currency": "USD", 
      "when": "20 days ago"
    }, 
    {
      "timestamp": "2017-09-06T00:00:41.195478Z", 
      "value": 0.05601, 
      "value.currency": "USD", 
      "when": "26 days ago"
    }, 
    {
      "timestamp": "2017-09-05T00:01:07.700426Z", 
      "value": 0.055262, 
      "value.currency": "USD", 
      "when": "27 days ago"
    }, 
    {
      "timestamp": "2017-09-04T00:00:27.463994Z", 
      "value": 0.059536, 
      "value.currency": "USD", 
      "when": "28 days ago"
    }, 
    {
      "timestamp": "2017-09-03T00:00:47.084020Z", 
      "value": 0.031658, 
      "value.currency": "USD", 
      "when": "29 days ago"
    }, 
    {
      "timestamp": "2017-09-02T00:00:49.937620Z", 
      "value": 0.055904, 
      "value.currency": "USD", 
      "when": "30 days ago"
    }, 
    {
      "timestamp": "2017-09-01T00:01:47.018408Z", 
      "value": 0.049567, 
      "value.currency": "USD", 
      "when": "a month ago"
    }, 
    {
      "timestamp": "2017-08-31T00:00:57.886790Z", 
      "value": 0.064408, 
      "value.currency": "USD", 
      "when": "a month ago"
    }, 
    {
      "timestamp": "2017-08-30T00:01:17.900185Z", 
      "value": 0.068957, 
      "value.currency": "USD", 
      "when": "a month ago"
    }, 
    {
      "timestamp": "2017-08-29T00:01:14.030819Z", 
      "value": 0.066553, 
      "value.currency": "USD", 
      "when": "a month ago"
    }, 
    {
      "timestamp": "2017-08-28T00:00:55.336814Z", 
      "value": 0.078043, 
      "value.currency": "USD", 
      "when": "a month ago"
    }, 
    {
      "timestamp": "2017-08-27T00:01:02.230334Z", 
      "value": 0.065715, 
      "value.currency": "USD", 
      "when": "a month ago"
    }, 
    {
      "timestamp": "2017-08-26T00:00:23.076762Z", 
      "value": 0.191438, 
      "value.currency": "USD", 
      "when": "a month ago"
    }, 
    {
      "timestamp": "2017-08-25T00:01:21.419892Z", 
      "value": 0.065467, 
      "value.currency": "USD", 
      "when": "a month ago"
    }, 
    {
      "timestamp": "2017-08-24T00:02:11.385908Z", 
      "value": 0.071043, 
      "value.currency": "USD", 
      "when": "a month ago"
    }, 
    {
      "timestamp": "2017-08-23T00:02:32.098382Z", 
      "value": 0.069605, 
      "value.currency": "USD", 
      "when": "a month ago"
    }, 
    {
      "timestamp": "2017-08-22T00:02:10.837211Z", 
      "value": 0.067859, 
      "value.currency": "USD", 
      "when": "a month ago"
    }, 
    {
      "timestamp": "2017-08-21T00:01:57.756376Z", 
      "value": 0.068415, 
      "value.currency": "USD", 
      "when": "a month ago"
    }, 
    {
      "timestamp": "2017-08-19T00:02:18.508450Z", 
      "value": 0.065158, 
      "value.currency": "USD", 
      "when": "a month ago"
    }, 
    {
      "timestamp": "2017-08-18T00:01:59.664864Z", 
      "value": 0.06865, 
      "value.currency": "USD", 
      "when": "a month ago"
    }, 
    {
      "timestamp": "2017-08-17T00:01:36.818457Z", 
      "value": 0.066377, 
      "value.currency": "USD", 
      "when": "a month ago"
    }, 
    {
      "timestamp": "2017-08-16T00:01:55.894521Z", 
      "value": 0.066387, 
      "value.currency": "USD", 
      "when": "a month ago"
    }, 
    {
      "timestamp": "2017-08-15T00:02:02.528299Z", 
      "value": 0.059626, 
      "value.currency": "USD", 
      "when": "a month ago"
    }, 
    {
      "timestamp": "2017-08-14T00:01:48.789245Z", 
      "value": 0.062622, 
      "value.currency": "USD", 
      "when": "a month ago"
    }, 
    {
      "timestamp": "2017-08-12T00:02:34.651040Z", 
      "value": 0.056019, 
      "value.currency": "USD", 
      "when": "a month ago"
    }, 
    {
      "timestamp": "2017-08-11T00:02:12.286624Z", 
      "value": 0.054262, 
      "value.currency": "USD", 
      "when": "a month ago"
    }, 
    {
      "timestamp": "2017-08-10T00:01:47.201340Z", 
      "value": 0.050708, 
      "value.currency": "USD", 
      "when": "a month ago"
    }, 
    {
      "timestamp": "2017-08-09T00:02:37.179259Z", 
      "value": 0.051897, 
      "value.currency": "USD", 
      "when": "a month ago"
    }, 
    {
      "timestamp": "2017-08-08T00:02:01.989212Z", 
      "value": 0.0514, 
      "value.currency": "USD", 
      "when": "a month ago"
    }, 
    {
      "timestamp": "2017-08-07T00:01:35.922917Z", 
      "value": 0.048959, 
      "value.currency": "USD", 
      "when": "a month ago"
    }, 
    {
      "timestamp": "2017-08-06T00:02:45.103486Z", 
      "value": 0.049368, 
      "value.currency": "USD", 
      "when": "a month ago"
    }, 
    {
      "timestamp": "2017-08-05T00:01:31.622126Z", 
      "value": 0.10824, 
      "value.currency": "USD", 
      "when": "a month ago"
    }, 
    {
      "timestamp": "2017-08-04T00:01:35.050175Z", 
      "value": 0.092333, 
      "value.currency": "USD", 
      "when": "a month ago"
    }, 
    {
      "timestamp": "2017-08-03T00:02:03.993751Z", 
      "value": 0.071776, 
      "value.currency": "USD", 
      "when": "a month ago"
    }, 
    {
      "timestamp": "2017-08-02T00:01:36.927434Z", 
      "value": 0.049145, 
      "value.currency": "USD", 
      "when": "2 months ago"
    }, 
    {
      "timestamp": "2017-08-01T00:02:07.038548Z", 
      "value": 0.049923, 
      "value.currency": "USD", 
      "when": "2 months ago"
    }, 
    {
      "timestamp": "2017-07-31T00:02:12.463564Z", 
      "value": 0.047774, 
      "value.currency": "USD", 
      "when": "2 months ago"
    }, 
    {
      "timestamp": "2017-07-30T00:01:54.261840Z", 
      "value": 0.040755, 
      "value.currency": "USD", 
      "when": "2 months ago"
    }, 
    {
      "timestamp": "2017-07-29T00:02:09.646816Z", 
      "value": 0.049651, 
      "value.currency": "USD", 
      "when": "2 months ago"
    }, 
    {
      "timestamp": "2017-07-28T00:02:31.527088Z", 
      "value": 0.045101, 
      "value.currency": "USD", 
      "when": "2 months ago"
    }, 
    {
      "timestamp": "2017-07-27T00:02:20.645663Z", 
      "value": 0.042851, 
      "value.currency": "USD", 
      "when": "2 months ago"
    }, 
    {
      "timestamp": "2017-07-26T00:02:35.066826Z", 
      "value": 0.038873, 
      "value.currency": "USD", 
      "when": "2 months ago"
    }, 
    {
      "timestamp": "2017-07-25T00:02:06.052864Z", 
      "value": 0.041928, 
      "value.currency": "USD", 
      "when": "2 months ago"
    }, 
    {
      "timestamp": "2017-07-24T00:02:06.911120Z", 
      "value": 0.041857, 
      "value.currency": "USD", 
      "when": "2 months ago"
    }, 
    {
      "timestamp": "2017-07-23T00:01:57.533212Z", 
      "value": 0.042938, 
      "value.currency": "USD", 
      "when": "2 months ago"
    }, 
    {
      "timestamp": "2017-07-22T00:01:39.241519Z", 
      "value": 0.064161, 
      "value.currency": "USD", 
      "when": "2 months ago"
    }, 
    {
      "timestamp": "2017-07-21T00:01:34.802556Z", 
      "value": 0.12734, 
      "value.currency": "USD", 
      "when": "2 months ago"
    }, 
    {
      "timestamp": "2017-07-20T00:02:16.462083Z", 
      "value": 0.051856, 
      "value.currency": "USD", 
      "when": "2 months ago"
    }, 
    {
      "timestamp": "2017-07-19T00:01:55.733230Z", 
      "value": 0.055384, 
      "value.currency": "USD", 
      "when": "2 months ago"
    }, 
    {
      "timestamp": "2017-07-18T00:01:54.752955Z", 
      "value": 0.058755, 
      "value.currency": "USD", 
      "when": "2 months ago"
    }, 
    {
      "timestamp": "2017-07-17T00:01:50.525025Z", 
      "value": 0.050428, 
      "value.currency": "USD", 
      "when": "2 months ago"
    }, 
    {
      "timestamp": "2017-07-16T00:01:44.507544Z", 
      "value": 0.049166, 
      "value.currency": "USD", 
      "when": "2 months ago"
    }, 
    {
      "timestamp": "2017-07-15T00:01:58.290748Z", 
      "value": 0.06013, 
      "value.currency": "USD", 
      "when": "2 months ago"
    }, 
    {
      "timestamp": "2017-07-14T00:02:00.803995Z", 
      "value": 0.06953, 
      "value.currency": "USD", 
      "when": "2 months ago"
    }, 
    {
      "timestamp": "2017-07-12T00:01:47.255514Z", 
      "value": 0.063406, 
      "value.currency": "USD", 
      "when": "2 months ago"
    }, 
    {
      "timestamp": "2017-07-11T00:02:55.517385Z", 
      "value": 0.060111, 
      "value.currency": "USD", 
      "when": "2 months ago"
    }, 
    {
      "timestamp": "2017-07-10T00:01:49.823339Z", 
      "value": 0.064109, 
      "value.currency": "USD", 
      "when": "2 months ago"
    }, 
    {
      "timestamp": "2017-07-09T00:01:50.380864Z", 
      "value": 0.068306, 
      "value.currency": "USD", 
      "when": "2 months ago"
    }, 
    {
      "timestamp": "2017-07-08T00:01:37.966599Z", 
      "value": 0.066445, 
      "value.currency": "USD", 
      "when": "2 months ago"
    }, 
    {
      "timestamp": "2017-07-07T00:01:53.788459Z", 
      "value": 0.158263, 
      "value.currency": "USD", 
      "when": "2 months ago"
    }, 
    {
      "timestamp": "2017-07-06T00:02:19.256072Z", 
      "value": 0.163699, 
      "value.currency": "USD", 
      "when": "2 months ago"
    }, 
    {
      "timestamp": "2017-07-05T00:01:45.955740Z", 
      "value": 0.087583, 
      "value.currency": "USD", 
      "when": "2 months ago"
    }, 
    {
      "timestamp": "2017-07-04T00:01:54.323807Z", 
      "value": 0.063196, 
      "value.currency": "USD", 
      "when": "2 months ago"
    }, 
    {
      "timestamp": "2017-07-03T00:01:46.023686Z", 
      "value": 0.060331, 
      "value.currency": "USD", 
      "when": "2 months ago"
    }, 
    {
      "timestamp": "2017-07-02T00:01:59.688713Z", 
      "value": 0.091861, 
      "value.currency": "USD", 
      "when": "3 months ago"
    }, 
    {
      "timestamp": "2017-07-01T00:01:33.213573Z", 
      "value": 0.081122, 
      "value.currency": "USD", 
      "when": "3 months ago"
    }, 
    {
      "timestamp": "2017-06-29T00:01:18.147174Z", 
      "value": 0.080538, 
      "value.currency": "USD", 
      "when": "3 months ago"
    }, 
    {
      "timestamp": "2017-06-28T00:02:05.245357Z", 
      "value": 0.072875, 
      "value.currency": "USD", 
      "when": "3 months ago"
    }, 
    {
      "timestamp": "2017-06-26T00:01:51.856905Z", 
      "value": 0.186958, 
      "value.currency": "USD", 
      "when": "3 months ago"
    }, 
    {
      "timestamp": "2017-06-25T00:01:45.950837Z", 
      "value": 0.108459, 
      "value.currency": "USD", 
      "when": "3 months ago"
    }, 
    {
      "timestamp": "2017-06-24T00:01:42.008881Z", 
      "value": 0.087198, 
      "value.currency": "USD", 
      "when": "3 months ago"
    }, 
    {
      "timestamp": "2017-06-23T00:01:58.432654Z", 
      "value": 0.092458, 
      "value.currency": "USD", 
      "when": "3 months ago"
    }, 
    {
      "timestamp": "2017-06-22T00:01:45.862882Z", 
      "value": 0.092746, 
      "value.currency": "USD", 
      "when": "3 months ago"
    }, 
    {
      "timestamp": "2017-06-21T00:02:03.496364Z", 
      "value": 0.067446, 
      "value.currency": "USD", 
      "when": "3 months ago"
    }, 
    {
      "timestamp": "2017-06-20T00:02:33.818371Z", 
      "value": 0.05501, 
      "value.currency": "USD", 
      "when": "3 months ago"
    }, 
    {
      "timestamp": "2017-06-19T00:01:25.971075Z", 
      "value": 0.057976, 
      "value.currency": "USD", 
      "when": "3 months ago"
    }, 
    {
      "timestamp": "2017-06-18T00:01:22.830471Z", 
      "value": 0.054881, 
      "value.currency": "USD", 
      "when": "3 months ago"
    }, 
    {
      "timestamp": "2017-06-17T00:01:47.682653Z", 
      "value": 0.043867, 
      "value.currency": "USD", 
      "when": "3 months ago"
    }, 
    {
      "timestamp": "2017-06-16T00:01:56.055837Z", 
      "value": 0.060389, 
      "value.currency": "USD", 
      "when": "3 months ago"
    }, 
    {
      "timestamp": "2017-06-15T00:02:04.323889Z", 
      "value": 0.119139, 
      "value.currency": "USD", 
      "when": "3 months ago"
    }, 
    {
      "timestamp": "2017-06-14T00:02:16.811382Z", 
      "value": 0.031431, 
      "value.currency": "USD", 
      "when": "3 months ago"
    }, 
    {
      "timestamp": "2017-06-13T00:01:51.992175Z", 
      "value": 0.054169, 
      "value.currency": "USD", 
      "when": "3 months ago"
    }, 
    {
      "timestamp": "2017-06-12T00:01:35.461264Z", 
      "value": 0.073425, 
      "value.currency": "USD", 
      "when": "3 months ago"
    }, 
    {
      "timestamp": "2017-06-11T00:01:44.031949Z", 
      "value": 0.095802, 
      "value.currency": "USD", 
      "when": "3 months ago"
    }, 
    {
      "timestamp": "2017-06-10T00:01:54.966612Z", 
      "value": 0.147145, 
      "value.currency": "USD", 
      "when": "3 months ago"
    }, 
    {
      "timestamp": "2017-06-09T00:01:37.840935Z", 
      "value": 0.195872, 
      "value.currency": "USD", 
      "when": "3 months ago"
    }, 
    {
      "timestamp": "2017-06-08T00:01:36.526876Z", 
      "value": 0.199272, 
      "value.currency": "USD", 
      "when": "3 months ago"
    }, 
    {
      "timestamp": "2017-06-07T00:01:59.913538Z", 
      "value": 0.120377, 
      "value.currency": "USD", 
      "when": "3 months ago"
    }, 
    {
      "timestamp": "2017-06-06T00:01:28.327243Z", 
      "value": 0.139807, 
      "value.currency": "USD", 
      "when": "3 months ago"
    }, 
    {
      "timestamp": "2017-06-05T00:01:38.877606Z", 
      "value": 0.151232, 
      "value.currency": "USD", 
      "when": "3 months ago"
    }, 
    {
      "timestamp": "2017-06-04T00:01:28.827071Z", 
      "value": 0.303989, 
      "value.currency": "USD", 
      "when": "3 months ago"
    }, 
    {
      "timestamp": "2017-06-03T00:01:18.400794Z", 
      "value": 0.247916, 
      "value.currency": "USD", 
      "when": "3 months ago"
    }, 
    {
      "timestamp": "2017-06-02T00:01:14.277131Z", 
      "value": 0.095373, 
      "value.currency": "USD", 
      "when": "4 months ago"
    }, 
    {
      "timestamp": "2017-06-01T00:01:16.516135Z", 
      "value": 0.124244, 
      "value.currency": "USD", 
      "when": "4 months ago"
    }, 
    {
      "timestamp": "2017-05-31T00:01:25.188816Z", 
      "value": 0.063764, 
      "value.currency": "USD", 
      "when": "4 months ago"
    }, 
    {
      "timestamp": "2017-05-30T00:01:12.533792Z", 
      "value": 0.04682, 
      "value.currency": "USD", 
      "when": "4 months ago"
    }, 
    {
      "timestamp": "2017-05-29T00:01:22.647252Z", 
      "value": 0.130162, 
      "value.currency": "USD", 
      "when": "4 months ago"
    }, 
    {
      "timestamp": "2017-05-28T00:01:20.921682Z", 
      "value": 0.160193, 
      "value.currency": "USD", 
      "when": "4 months ago"
    }, 
    {
      "timestamp": "2017-05-27T00:01:21.731250Z", 
      "value": 0.116087, 
      "value.currency": "USD", 
      "when": "4 months ago"
    }, 
    {
      "timestamp": "2017-05-26T00:01:05.608057Z", 
      "value": 0.16316, 
      "value.currency": "USD", 
      "when": "4 months ago"
    }, 
    {
      "timestamp": "2017-05-25T00:01:29.328989Z", 
      "value": 0.172992, 
      "value.currency": "USD", 
      "when": "4 months ago"
    }, 
    {
      "timestamp": "2017-05-24T00:01:38.485859Z", 
      "value": 0.372813, 
      "value.currency": "USD", 
      "when": "4 months ago"
    }, 
    {
      "timestamp": "2017-05-23T00:01:15.969206Z", 
      "value": 0.118006, 
      "value.currency": "USD", 
      "when": "4 months ago"
    }, 
    {
      "timestamp": "2017-05-22T00:01:04.265429Z", 
      "value": 0.590603, 
      "value.currency": "USD", 
      "when": "4 months ago"
    }, 
    {
      "timestamp": "2017-05-21T00:01:19.067262Z", 
      "value": 0.113667, 
      "value.currency": "USD", 
      "when": "4 months ago"
    }, 
    {
      "timestamp": "2017-05-20T00:01:17.440876Z", 
      "value": 0.063927, 
      "value.currency": "USD", 
      "when": "4 months ago"
    }, 
    {
      "timestamp": "2017-05-19T00:01:54.779382Z", 
      "value": 0.070224, 
      "value.currency": "USD", 
      "when": "4 months ago"
    }, 
    {
      "timestamp": "2017-05-18T00:00:58.908899Z", 
      "value": 0.102664, 
      "value.currency": "USD", 
      "when": "4 months ago"
    }, 
    {
      "timestamp": "2017-05-17T00:01:07.465929Z", 
      "value": 0.366844, 
      "value.currency": "USD", 
      "when": "4 months ago"
    }, 
    {
      "timestamp": "2017-05-16T00:01:06.746985Z", 
      "value": 0.140558, 
      "value.currency": "USD", 
      "when": "4 months ago"
    }, 
    {
      "timestamp": "2017-05-15T00:01:33.536409Z", 
      "value": 0.339552, 
      "value.currency": "USD", 
      "when": "4 months ago"
    }, 
    {
      "timestamp": "2017-05-14T00:01:28.974107Z", 
      "value": 0.442455, 
      "value.currency": "USD", 
      "when": "4 months ago"
    }, 
    {
      "timestamp": "2017-05-13T00:01:20.511719Z", 
      "value": 0.493932, 
      "value.currency": "USD", 
      "when": "4 months ago"
    }, 
    {
      "timestamp": "2017-05-12T00:01:01.151695Z", 
      "value": 0.324985, 
      "value.currency": "USD", 
      "when": "4 months ago"
    }, 
    {
      "timestamp": "2017-05-11T00:01:28.189391Z", 
      "value": 0.237738, 
      "value.currency": "USD", 
      "when": "4 months ago"
    }, 
    {
      "timestamp": "2017-05-10T00:01:07.131253Z", 
      "value": 1.29, 
      "value.currency": "USD", 
      "when": "4 months ago"
    }
  ]
}
